{"body":[[{"cmd":"SEND_GIFT","data":{"action":"投喂","batch_combo_id":"batch:gift:combo_id:438090148:1398337493:32590:1674826547.6790","batch_combo_send":null,"beatId":"","biz_source":"live","blind_gift":null,"broadcast_id":0,"coin_type":"gold","combo_resources_id":1,"combo_send":null,"combo_stay_time":3,"combo_total_coin":300,"crit_prob":0,"demarcation":1,"discount_price":100,"dmscore":8,"draw":0,"effect":0,"effect_block":0,"face":"https://i1.hdslb.com/bfs/face/61b1be67f49972ffc711714cc40540389922157f.jpg","face_effect_id":0,"face_effect_type":0,"float_sc_resource_id":0,"giftId":32590,"giftName":"团圆扇","giftType":0,"gold":0,"guard_level":0,"is_first":false,"is_join_receiver":false,"is_naming":false,"is_special_batch":0,"magnification":1,"medal_info":{"anchor_roomid":0,"anchor_uname":"","guard_level":0,"icon_id":0,"is_lighted":0,"medal_color":0,"medal_color_border":0,"medal_color_end":0,"medal_color_start":0,"medal_level":0,"medal_name":"","special":"","target_id":0},"name_color":"","num":1,"original_gift_name":"","price":100,"rcost":5240855,"receive_user_info":{"uid":1398337493,"uname":"鲸鱼娘西丝特official"},"remain":0,"rnd":"1674826548121800001","send_master":null,"silver":0,"super":0,"super_batch_gift_num":3,"super_gift_num":3,"svga_block":0,"switch":true,"tag_image":"","tid":"1674826548121800001","timestamp":1674826548,"top_list":null,"total_coin":100,"uid":438090148,"uname":"东方大弥超可爱"}},{"cmd":"DANMU_MSG","info":[[0,1,25,16777215,1674826548823,1120984420,0,"871fd446",0,0,0,"",0,"{}","{}",{"mode":0,"show_player_type":0,"extra":"{\"send_from_me\":false,\"mode\":0,\"color\":16777215,\"dm_type\":0,\"font_size\":25,\"player_mode\":1,\"show_player_type\":0,\"content\":\"真够非的\",\"user_hash\":\"2267010118\",\"emoticon_unique\":\"\",\"bulge_display\":0,\"recommend_score\":8,\"main_state_dm_color\":\"\",\"objective_state_dm_color\":\"\",\"direction\":0,\"pk_direction\":0,\"quartet_direction\":0,\"anniversary_crowd\":0,\"yeah_space_type\":\"\",\"yeah_space_url\":\"\",\"jump_to_url\":\"\",\"space_type\":\"\",\"space_url\":\"\",\"animation\":{},\"emots\":null}"},{"activity_identity":"","activity_source":0,"not_show":0}],"真够非的",[689648592,"牧鹿之匙",0,0,0,10000,1,""],[],[0,0,9868950,">50000",0],["",""],0,0,null,{"ts":1674826548,"ct":"3A7E24C7"},0,0,null,null,0,7]},{"cmd":"DANMU_MSG","info":[[0,1,25,5566168,1674826548830,1674826259,0,"2dae46a0",0,0,0,"",0,"{}","{}",{"mode":0,"show_player_type":0,"extra":"{\"send_from_me\":false,\"mode\":0,\"color\":5566168,\"dm_type\":0,\"font_size\":25,\"player_mode\":1,\"show_player_type\":0,\"content\":\"幽灵姐妹\",\"user_hash\":\"766396064\",\"emoticon_unique\":\"\",\"bulge_display\":0,\"recommend_score\":0,\"main_state_dm_color\":\"\",\"objective_state_dm_color\":\"\",\"direction\":0,\"pk_direction\":0,\"quartet_direction\":0,\"anniversary_crowd\":0,\"yeah_space_type\":\"\",\"yeah_space_url\":\"\",\"jump_to_url\":\"\",\"space_type\":\"\",\"space_url\":\"\",\"animation\":{},\"emots\":null}"},{"activity_identity":"","activity_source":0,"not_show":0}],"幽灵姐妹",[609732868,"砬手残",0,0,0,10000,1,""],[6,"正鲸人","鲸鱼娘西丝特official",26545331,6126494,"",0,6126494,6126494,6126494,0,1,1398337493],[0,0,9868950,">50000",0],["",""],0,0,null,{"ts":1674826548,"ct":"62CE0DA0"},0,0,null,null,0,35]},{"cmd":"SEND_GIFT","data":{"action":"投喂","batch_combo_id":"","batch_combo_send":null,"beatId":"","biz_source":"live","blind_gift":null,"broadcast_id":0,"coin_type":"silver","combo_resources_id":1,"combo_send":null,"combo_stay_time":3,"combo_total_coin":0,"crit_prob":0,"demarcation":1,"discount_price":0,"dmscore":4,"draw":0,"effect":0,"effect_block":1,"face":"https://i2.hdslb.com/bfs/face/2a173dd01e148ff95efda9a03520ba553c19dc28.jpg","face_effect_id":0,"face_effect_type":0,"float_sc_resource_id":0,"giftId":1,"giftName":"辣条","giftType":5,"gold":0,"guard_level":0,"is_first":true,"is_join_receiver":false,"is_naming":false,"is_special_batch":0,"magnification":1,"medal_info":{"anchor_roomid":0,"anchor_uname":"","guard_level":0,"icon_id":0,"is_lighted":0,"medal_color":0,"medal_color_border":0,"medal_color_end":0,"medal_color_start":0,"medal_level":0,"medal_name":"","special":"","target_id":0},"name_color":"","num":1,"original_gift_name":"","price":100,"rcost":5240855,"receive_user_info":{"uid":1398337493,"uname":"鲸鱼娘西丝特official"},"remain":0,"rnd":"1674826548120700007","send_master":null,"silver":0,"super":0,"super_batch_gift_num":0,"super_gift_num":0,"svga_block":0,"switch":true,"tag_image":"","tid":"1674826548120700007","timestamp":1674826548,"top_list":null,"total_coin":100,"uid":75513887,"uname":"陈謀"}},{"cmd":"DANMU_MSG","info":[[0,4,25,9920249,1674826548854,1113928292,0,"72003d1c",0,0,2,"#19897EFF,#403F388E,#33897EFF",0,"{}","{}",{"mode":0,"show_player_type":0,"extra":"{\"send_from_me\":false,\"mode\":0,\"color\":9920249,\"dm_type\":0,\"font_size\":25,\"player_mode\":4,\"show_player_type\":0,\"content\":\"能不能做个正鲸人！\",\"user_hash\":\"1912618268\",\"emoticon_unique\":\"\",\"bulge_display\":0,\"recommend_score\":6,\"main_state_dm_color\":\"\",\"objective_state_dm_color\":\"\",\"direction\":0,\"pk_direction\":0,\"quartet_direction\":0,\"anniversary_crowd\":0,\"yeah_space_type\":\"\",\"yeah_space_url\":\"\",\"jump_to_url\":\"\",\"space_type\":\"\",\"space_url\":\"\",\"animation\":{},\"emots\":null}"},{"activity_identity":"","activity_source":0,"not_show":0}],"能不能做个正鲸人！",[3493079266887905,"折纸der宁",0,0,0,10000,1,"#E17AFF"],[27,"正鲸人","鲸鱼娘西丝特official",26545331,398668,"",0,16771156,398668,6850801,2,1,1398337493],[20,0,6406234,">50000",1],["title-635-1","title-635-1"],0,2,null,{"ts":1674826548,"ct":"BEEA5C00"},0,0,null,null,0,112]},{"cmd":"DANMU_MSG","info":[[0,1,25,16777215,1674826548878,731162077,0,"bfa07659",0,0,0,"",1,{"bulge_display":0,"emoticon_unique":"official_109","height":60,"in_player_area":1,"is_dynamic":1,"url":"http://i0.hdslb.com/bfs/live/7b7a2567ad1520f962ee226df777eaf3ca368fbc.png","width":138},"{}",{"mode":0,"show_player_type":0,"extra":"{\"send_from_me\":false,\"mode\":0,\"color\":16777215,\"dm_type\":1,\"font_size\":25,\"player_mode\":1,\"show_player_type\":0,\"content\":\"妙啊\",\"user_hash\":\"3214964313\",\"emoticon_unique\":\"official_109\",\"bulge_display\":0,\"recommend_score\":6,\"main_state_dm_color\":\"\",\"objective_state_dm_color\":\"\",\"direction\":0,\"pk_direction\":0,\"quartet_direction\":0,\"anniversary_crowd\":0,\"yeah_space_type\":\"\",\"yeah_space_url\":\"\",\"jump_to_url\":\"\",\"space_type\":\"\",\"space_url\":\"\",\"animation\":{},\"emots\":null}"},{"activity_identity":"","activity_source":0,"not_show":0}],"妙啊",[269519889,"斯克文",0,0,0,10000,1,""],[5,"小马车","老火车托马斯",12110323,6126494,"",0,12632256,12632256,12632256,0,0,18906831],[1,0,9868950,">50000",0],["",""],0,0,null,{"ts":1674826548,"ct":"491D826C"},0,0,null,null,0,21]},{"cmd":"SEND_GIFT","data":{"action":"投喂","batch_combo_id":"batch:gift:combo_id:670973560:1398337493:30869:1674826545.9590","batch_combo_send":null,"beatId":"","biz_source":"live","blind_gift":null,"broadcast_id":0,"coin_type":"gold","combo_resources_id":1,"combo_send":null,"combo_stay_time":3,"combo_total_coin":300,"crit_prob":0,"demarcation":1,"discount_price":100,"dmscore":56,"draw":0,"effect":0,"effect_block":0,"face":"https://i1.hdslb.com/bfs/face/05685ff6010639605b1fff93c4d8b531f1d16bb2.jpg","face_effect_id":0,"face_effect_type":0,"float_sc_resource_id":0,"giftId":30869,"giftName":"心动卡","giftType":0,"gold":0,"guard_level":0,"is_first":false,"is_join_receiver":false,"is_naming":false,"is_special_batch":0,"magnification":1,"medal_info":{"anchor_roomid":0,"anchor_uname":"","guard_level":0,"icon_id":0,"is_lighted":1,"medal_color":9272486,"medal_color_border":9272486,"medal_color_end":9272486,"medal_color_start":9272486,"medal_level":10,"medal_name":"正鲸人","special":"","target_id":1398337493},"name_color":"","num":1,"original_gift_name":"","price":100,"rcost":5240855,"receive_user_info":{"uid":1398337493,"uname":"鲸鱼娘西丝特official"},"remain":0,"rnd":"1674826548131000003","send_master":null,"silver":0,"super":0,"super_batch_gift_num":3,"super_gift_num":3,"svga_block":0,"switch":true,"tag_image":"","tid":"1674826548131000003","timestamp":1674826548,"top_list":null,"total_coin":100,"uid":670973560,"uname":"有在记着冉冉"}},{"cmd":"SEND_GIFT","data":{"action":"投喂","batch_combo_id":"","batch_combo_send":null,"beatId":"","biz_source":"Live","blind_gift":null,"broadcast_id":0,"coin_type":"silver","combo_resources_id":1,"combo_send":null,"combo_stay_time":3,"combo_total_coin":0,"crit_prob":0,"demarcation":1,"discount_price":0,"dmscore":4,"draw":0,"effect":0,"effect_block":1,"face":"https://i1.hdslb.com/bfs/face/d615ea19a3bab1bec5df3a50d477bf4a08ef9671.jpg","face_effect_id":0,"face_effect_type":0,"float_sc_resource_id":0,"giftId":1,"giftName":"辣条","giftType":5,"gold":0,"guard_level":0,"is_first":true,"is_join_receiver":false,"is_naming":false,"is_special_batch":0,"magnification":1,"medal_info":{"anchor_roomid":0,"anchor_uname":"","guard_level":0,"icon_id":0,"is_lighted":0,"medal_color":0,"medal_color_border":0,"medal_color_end":0,"medal_color_start":0,"medal_level":0,"medal_name":"","special":"","target_id":0},"name_color":"","num":1,"original_gift_name":"","price":100,"rcost":5240877,"receive_user_info":{"uid":1398337493,"uname":"鲸鱼娘西丝特official"},"remain":0,"rnd":"1674826548120300011","send_master":null,"silver":0,"super":0,"super_batch_gift_num":0,"super_gift_num":0,"svga_block":0,"switch":true,"tag_image":"","tid":"1674826548120300011","timestamp":1674826548,"top_list":null,"total_coin":100,"uid":3493091801565823,"uname":"-露桑-"}},{"cmd":"SEND_GIFT","data":{"action":"投喂","batch_combo_id":"","batch_combo_send":null,"beatId":"","biz_source":"live","blind_gift":null,"broadcast_id":0,"coin_type":"silver","combo_resources_id":1,"combo_send":null,"combo_stay_time":3,"combo_total_coin":0,"crit_prob":0,"demarcation":1,"discount_price":0,"dmscore":16,"draw":0,"effect":0,"effect_block":1,"face":"https://i1.hdslb.com/bfs/face/487ab8c1bd6c0aadb7e275aed02d0945f80db6b1.jpg","face_effect_id":0,"face_effect_type":0,"float_sc_resource_id":0,"giftId":1,"giftName":"辣条","giftType":5,"gold":0,"guard_level":0,"is_first":true,"is_join_receiver":false,"is_naming":false,"is_special_batch":0,"magnification":1,"medal_info":{"anchor_roomid":0,"anchor_uname":"","guard_level":0,"icon_id":0,"is_lighted":1,"medal_color":6067854,"medal_color_border":6067854,"medal_color_end":6067854,"medal_color_start":6067854,"medal_level":4,"medal_name":"正鲸人","special":"","target_id":1398337493},"name_color":"","num":1,"original_gift_name":"","price":100,"rcost":5240877,"receive_user_info":{"uid":1398337493,"uname":"鲸鱼娘西丝特official"},"remain":0,"rnd":"1674826548120000002","send_master":null,"silver":0,"super":0,"super_batch_gift_num":0,"super_gift_num":0,"svga_block":0,"switch":true,"tag_image":"","tid":"1674826548120000002","timestamp":1674826548,"top_list":null,"total_coin":100,"uid":349152160,"uname":"WEAK_GOD"}},{"cmd":"DANMU_MSG","info":[[0,1,25,16777215,1674826549005,-1323735684,0,"31351eec",0,0,0,"",0,"{}","{}",{"mode":0,"show_player_type":0,"extra":"{\"send_from_me\":false,\"mode\":0,\"color\":16777215,\"dm_type\":0,\"font_size\":25,\"player_mode\":1,\"show_player_type\":0,\"content\":\"？\",\"user_hash\":\"825564908\",\"emoticon_unique\":\"\",\"bulge_display\":0,\"recommend_score\":6,\"main_state_dm_color\":\"\",\"objective_state_dm_color\":\"\",\"direction\":0,\"pk_direction\":0,\"quartet_direction\":0,\"anniversary_crowd\":0,\"yeah_space_type\":\"\",\"yeah_space_url\":\"\",\"jump_to_url\":\"\",\"space_type\":\"\",\"space_url\":\"\",\"animation\":{},\"emots\":null}"},{"activity_identity":"","activity_source":0,"not_show":0}],"？",[310405700,"沂橙子",0,0,0,10000,1,""],[4,"正鲸人","鲸鱼娘西丝特official",26545331,6067854,"",0,6067854,6067854,6067854,0,1,1398337493],[11,0,6406234,">50000",0],["",""],0,0,null,{"ts":1674826549,"ct":"823BC61"},0,0,null,null,0,28]},{"cmd":"SEND_GIFT","data":{"action":"投喂","batch_combo_id":"","batch_combo_send":null,"beatId":"","biz_source":"live","blind_gift":null,"broadcast_id":0,"coin_type":"silver","combo_resources_id":1,"combo_send":null,"combo_stay_time":3,"combo_total_coin":0,"crit_prob":0,"demarcation":1,"discount_price":0,"dmscore":4,"draw":0,"effect":0,"effect_block":1,"face":"https://i2.hdslb.com/bfs/face/91ba336c4ac058553525a5b296c25672f5dc39bc.jpg","face_effect_id":0,"face_effect_type":0,"float_sc_resource_id":0,"giftId":1,"giftName":"辣条","giftType":5,"gold":0,"guard_level":0,"is_first":true,"is_join_receiver":false,"is_naming":false,"is_special_batch":0,"magnification":1,"medal_info":{"anchor_roomid":0,"anchor_uname":"","guard_level":0,"icon_id":0,"is_lighted":0,"medal_color":0,"medal_color_border":0,"medal_color_end":0,"medal_color_start":0,"medal_level":0,"medal_name":"","special":"","target_id":0},"name_color":"","num":23,"original_gift_name":"","price":100,"rcost":5240899,"receive_user_info":{"uid":1398337493,"uname":"鲸鱼娘西丝特official"},"remain":0,"rnd":"1674826548120400005","send_master":null,"silver":0,"super":0,"super_batch_gift_num":0,"super_gift_num":0,"svga_block":0,"switch":true,"tag_image":"","tid":"1674826548120400005","timestamp":1674826548,"top_list":null,"total_coin":2300,"uid":1374407564,"uname":"bili_64088975739"}},{"cmd":"INTERACT_WORD","data":{"contribution":{"grade":0},"core_user_type":0,"dmscore":20,"fans_medal":{"anchor_roomid":26213288,"guard_level":3,"icon_id":0,"is_lighted":1,"medal_color":1725515,"medal_color_border":6809855,"medal_color_end":5414290,"medal_color_start":1725515,"medal_level":24,"medal_name":"真黎葡","score":50012982,"special":"","target_id":3461578781362279},"identities":[3,1],"is_spread":0,"msg_type":1,"privilege_type":0,"roomid":26545331,"score":1724849530035,"spread_desc":"","spread_info":"","tail_icon":0,"timestamp":1674826548,"trigger_time":1674826546972112100,"uid":10774091,"uname":"机构研究研究","uname_color":""}},{"cmd":"INTERACT_WORD","data":{"contribution":{"grade":0},"core_user_type":0,"dmscore":20,"fans_medal":{"anchor_roomid":23770996,"guard_level":3,"icon_id":0,"is_lighted":1,"medal_color":1725515,"medal_color_border":6809855,"medal_color_end":5414290,"medal_color_start":1725515,"medal_level":22,"medal_name":"向心梨","score":50004151,"special":"","target_id":1900141897},"identities":[3,1],"is_spread":0,"msg_type":1,"privilege_type":0,"roomid":26545331,"score":1724840699476,"spread_desc":"","spread_info":"","tail_icon":0,"timestamp":1674826548,"trigger_time":1674826547325980700,"uid":471603430,"uname":"台灯且烯烃","uname_color":""}},{"cmd":"SEND_GIFT","data":{"action":"投喂","batch_combo_id":"batch:gift:combo_id:351171220:1398337493:32345:1674826535.8373","batch_combo_send":null,"beatId":"","biz_source":"live","blind_gift":null,"broadcast_id":0,"coin_type":"gold","combo_resources_id":1,"combo_send":null,"combo_stay_time":3,"combo_total_coin":6600,"crit_prob":0,"demarcation":1,"discount_price":100,"dmscore":56,"draw":0,"effect":0,"effect_block":0,"face":"https://i1.hdslb.com/bfs/face/0b5c367a3a04e3d431529db6b8f2d63e113c251a.jpg","face_effect_id":0,"face_effect_type":0,"float_sc_resource_id":0,"giftId":32345,"giftName":"人气票","giftType":0,"gold":0,"guard_level":0,"is_first":false,"is_join_receiver":false,"is_naming":false,"is_special_batch":0,"magnification":1.2,"medal_info":{"anchor_roomid":0,"anchor_uname":"","guard_level":0,"icon_id":0,"is_lighted":1,"medal_color":9272486,"medal_color_border":9272486,"medal_color_end":9272486,"medal_color_start":9272486,"medal_level":10,"medal_name":"正鲸人","special":"","target_id":1398337493},"name_color":"","num":1,"original_gift_name":"","price":100,"rcost":5240877,"receive_user_info":{"uid":1398337493,"uname":"鲸鱼娘西丝特official"},"remain":0,"rnd":"1674826549121000001","send_master":null,"silver":0,"super":0,"super_batch_gift_num":66,"super_gift_num":66,"svga_block":0,"switch":true,"tag_image":"","tid":"1674826549121000001","timestamp":1674826549,"top_list":null,"total_coin":100,"uid":351171220,"uname":"OUO-13"}},{"cmd":"SEND_GIFT","data":{"action":"投喂","batch_combo_id":"batch:gift:combo_id:438090148:1398337493:32590:1674826547.6790","batch_combo_send":null,"beatId":"","biz_source":"live","blind_gift":null,"broadcast_id":0,"coin_type":"gold","combo_resources_id":1,"combo_send":null,"combo_stay_time":3,"combo_total_coin":400,"crit_prob":0,"demarcation":1,"discount_price":100,"dmscore":8,"draw":0,"effect":0,"effect_block":0,"face":"https://i1.hdslb.com/bfs/face/61b1be67f49972ffc711714cc40540389922157f.jpg","face_effect_id":0,"face_effect_type":0,"float_sc_resource_id":0,"giftId":32590,"giftName":"团圆扇","giftType":0,"gold":0,"guard_level":0,"is_first":false,"is_join_receiver":false,"is_naming":false,"is_special_batch":0,"magnification":1,"medal_info":{"anchor_roomid":0,"anchor_uname":"","guard_level":0,"icon_id":0,"is_lighted":0,"medal_color":0,"medal_color_border":0,"medal_color_end":0,"medal_color_start":0,"medal_level":0,"medal_name":"","special":"","target_id":0},"name_color":"","num":1,"original_gift_name":"","price":100,"rcost":5240877,"receive_user_info":{"uid":1398337493,"uname":"鲸鱼娘西丝特official"},"remain":0,"rnd":"1674826549121800001","send_master":null,"silver":0,"super":0,"super_batch_gift_num":4,"super_gift_num":4,"svga_block":0,"switch":true,"tag_image":"","tid":"1674826549121800001","timestamp":1674826549,"top_list":null,"total_coin":100,"uid":438090148,"uname":"东方大弥超可爱"}},{"cmd":"ENTRY_EFFECT","data":{"id":4,"uid":14665685,"target_id":1398337493,"mock_effect":0,"face":"https://i2.hdslb.com/bfs/face/effae20f0fb26585a88bb64bf32814686569aff5.jpg","privilege_type":3,"copy_writing":"欢迎舰长 <%嗨丝尊者%> 进入直播间","copy_color":"#ffffff","highlight_color":"#E6FF00","priority":1,"basemap_url":"https://i0.hdslb.com/bfs/live/mlive/11a6e8eb061c3e715d0a6a2ac0ddea2faa15c15e.png","show_avatar":1,"effective_time":2,"web_basemap_url":"https://i0.hdslb.com/bfs/live/mlive/11a6e8eb061c3e715d0a6a2ac0ddea2faa15c15e.png","web_effective_time":2,"web_effect_close":0,"web_close_time":0,"business":1,"copy_writing_v2":"欢迎舰长 <%嗨丝尊者%> 进入直播间","icon_list":[],"max_delay_time":7,"trigger_time":1674826547897388300,"identities":6,"effect_silent_time":0,"effective_time_new":0,"web_dynamic_url_webp":"","web_dynamic_url_apng":"","mobile_dynamic_url_webp":""}},{"cmd":"SEND_GIFT","data":{"action":"投喂","batch_combo_id":"","batch_combo_send":null,"beatId":"","biz_source":"live","blind_gift":null,"broadcast_id":0,"coin_type":"silver","combo_resources_id":1,"combo_send":null,"combo_stay_time":3,"combo_total_coin":0,"crit_prob":0,"demarcation":1,"discount_price":0,"dmscore":4,"draw":0,"effect":0,"effect_block":1,"face":"https://i2.hdslb.com/bfs/face/2a173dd01e148ff95efda9a03520ba553c19dc28.jpg","face_effect_id":0,"face_effect_type":0,"float_sc_resource_id":0,"giftId":1,"giftName":"辣条","giftType":5,"gold":0,"guard_level":0,"is_first":true,"is_join_receiver":false,"is_naming":false,"is_special_batch":0,"magnification":1,"medal_info":{"anchor_roomid":0,"anchor_uname":"","guard_level":0,"icon_id":0,"is_lighted":0,"medal_color":0,"medal_color_border":0,"medal_color_end":0,"medal_color_start":0,"medal_level":0,"medal_name":"","special":"","target_id":0},"name_color":"","num":1,"original_gift_name":"","price":100,"rcost":5240877,"receive_user_info":{"uid":1398337493,"uname":"鲸鱼娘西丝特official"},"remain":0,"rnd":"1674826548120700008","send_master":null,"silver":0,"super":0,"super_batch_gift_num":0,"super_gift_num":0,"svga_block":0,"switch":true,"tag_image":"","tid":"1674826548120700008","timestamp":1674826548,"top_list":null,"total_coin":100,"uid":75513887,"uname":"陈謀"}},{"cmd":"SEND_GIFT","data":{"action":"投喂","batch_combo_id":"batch:gift:combo_id:670973560:1398337493:30869:1674826545.9590","batch_combo_send":null,"beatId":"","biz_source":"live","blind_gift":null,"broadcast_id":0,"coin_type":"gold","combo_resources_id":1,"combo_send":null,"combo_stay_time":3,"combo_total_coin":400,"crit_prob":0,"demarcation":1,"discount_price":100,"dmscore":56,"draw":0,"effect":0,"effect_block":0,"face":"https://i1.hdslb.com/bfs/face/05685ff6010639605b1fff93c4d8b531f1d16bb2.jpg","face_effect_id":0,"face_effect_type":0,"float_sc_resource_id":0,"giftId":30869,"giftName":"心动卡","giftType":0,"gold":0,"guard_level":0,"is_first":false,"is_join_receiver":false,"is_naming":false,"is_special_batch":0,"magnification":1,"medal_info":{"anchor_roomid":0,"anchor_uname":"","guard_level":0,"icon_id":0,"is_lighted":1,"medal_color":9272486,"medal_color_border":9272486,"medal_color_end":9272486,"medal_color_start":9272486,"medal_level":10,"medal_name":"正鲸人","special":"","target_id":1398337493},"name_color":"","num":1,"original_gift_name":"","price":100,"rcost":5240877,"receive_user_info":{"uid":1398337493,"uname":"鲸鱼娘西丝特official"},"remain":0,"rnd":"1674826549131000001","send_master":null,"silver":0,"super":0,"super_batch_gift_num":4,"super_gift_num":4,"svga_block":0,"switch":true,"tag_image":"","tid":"1674826549131000001","timestamp":1674826549,"top_list":null,"total_coin":100,"uid":670973560,"uname":"有在记着冉冉"}},{"cmd":"SEND_GIFT","data":{"action":"投喂","batch_combo_id":"","batch_combo_send":null,"beatId":"","biz_source":"Live","blind_gift":null,"broadcast_id":0,"coin_type":"silver","combo_resources_id":1,"combo_send":null,"combo_stay_time":3,"combo_total_coin":0,"crit_prob":0,"demarcation":1,"discount_price":0,"dmscore":4,"draw":0,"effect":0,"effect_block":1,"face":"https://i1.hdslb.com/bfs/face/d615ea19a3bab1bec5df3a50d477bf4a08ef9671.jpg","face_effect_id":0,"face_effect_type":0,"float_sc_resource_id":0,"giftId":1,"giftName":"辣条","giftType":5,"gold":0,"guard_level":0,"is_first":true,"is_join_receiver":false,"is_naming":false,"is_special_batch":0,"magnification":1,"medal_info":{"anchor_roomid":0,"anchor_uname":"","guard_level":0,"icon_id":0,"is_lighted":0,"medal_color":0,"medal_color_border":0,"medal_color_end":0,"medal_color_start":0,"medal_level":0,"medal_name":"","special":"","target_id":0},"name_color":"","num":1,"original_gift_name":"","price":100,"rcost":5240877,"receive_user_info":{"uid":1398337493,"uname":"鲸鱼娘西丝特official"},"remain":0,"rnd":"1674826549120300002","send_master":null,"silver":0,"super":0,"super_batch_gift_num":0,"super_gift_num":0,"svga_block":0,"switch":true,"tag_image":"","tid":"1674826549120300002","timestamp":1674826549,"top_list":null,"total_coin":100,"uid":3493091801565823,"uname":"-露桑-"}},{"cmd":"DANMU_MSG","info":[[0,1,25,16777215,1674826549131,-404631041,0,"e144ff88",0,0,0,"",0,"{}","{}",{"mode":0,"show_player_type":0,"extra":"{\"send_from_me\":false,\"mode\":0,\"color\":16777215,\"dm_type\":0,\"font_size\":25,\"player_mode\":1,\"show_player_type\":0,\"content\":\"西门\",\"user_hash\":\"3779395464\",\"emoticon_unique\":\"\",\"bulge_display\":0,\"recommend_score\":2,\"main_state_dm_color\":\"\",\"objective_state_dm_color\":\"\",\"direction\":0,\"pk_direction\":0,\"quartet_direction\":0,\"anniversary_crowd\":0,\"yeah_space_type\":\"\",\"yeah_space_url\":\"\",\"jump_to_url\":\"\",\"space_type\":\"\",\"space_url\":\"\",\"animation\":{},\"emots\":null}"},{"activity_identity":"","activity_source":0,"not_show":0}],"西门",[477987452,"朝田诗乃彡",0,0,0,10000,1,""],[3,"有才","三十六贱笑",6031869,6067854,"",0,12632256,12632256,12632256,0,0,90361813],[0,0,9868950,">50000",0],["",""],0,0,null,{"ts":1674826549,"ct":"C6D61090"},0,0,null,null,0,14]},{"cmd":"SEND_GIFT","data":{"action":"投喂","batch_combo_id":"","batch_combo_send":null,"beatId":"","biz_source":"live","blind_gift":null,"broadcast_id":0,"coin_type":"silver","combo_resources_id":1,"combo_send":null,"combo_stay_time":3,"combo_total_coin":0,"crit_prob":0,"demarcation":1,"discount_price":0,"dmscore":16,"draw":0,"effect":0,"effect_block":1,"face":"https://i1.hdslb.com/bfs/face/487ab8c1bd6c0aadb7e275aed02d0945f80db6b1.jpg","face_effect_id":0,"face_effect_type":0,"float_sc_resource_id":0,"giftId":1,"giftName":"辣条","giftType":5,"gold":0,"guard_level":0,"is_first":true,"is_join_receiver":false,"is_naming":false,"is_special_batch":0,"magnification":1,"medal_info":{"anchor_roomid":0,"anchor_uname":"","guard_level":0,"icon_id":0,"is_lighted":1,"medal_color":6067854,"medal_color_border":6067854,"medal_color_end":6067854,"medal_color_start":6067854,"medal_level":4,"medal_name":"正鲸人","special":"","target_id":1398337493},"name_color":"","num":1,"original_gift_name":"","price":100,"rcost":5240877,"receive_user_info":{"uid":1398337493,"uname":"鲸鱼娘西丝特official"},"remain":0,"rnd":"1674826549120000001","send_master":null,"silver":0,"super":0,"super_batch_gift_num":0,"super_gift_num":0,"svga_block":0,"switch":true,"tag_image":"","tid":"1674826549120000001","timestamp":1674826549,"top_list":null,"total_coin":100,"uid":349152160,"uname":"WEAK_GOD"}},{"cmd":"SEND_GIFT","data":{"action":"投喂","batch_combo_id":"batch:gift:combo_id:351171220:1398337493:32345:1674826535.8373","batch_combo_send":null,"beatId":"","biz_source":"live","blind_gift":null,"broadcast_id":0,"coin_type":"gold","combo_resources_id":1,"combo_send":null,"combo_stay_time":3,"combo_total_coin":6700,"crit_prob":0,"demarcation":1,"discount_price":100,"dmscore":56,"draw":0,"effect":0,"effect_block":0,"face":"https://i1.hdslb.com/bfs/face/0b5c367a3a04e3d431529db6b8f2d63e113c251a.jpg","face_effect_id":0,"face_effect_type":0,"float_sc_resource_id":0,"giftId":32345,"giftName":"人气票","giftType":0,"gold":0,"guard_level":0,"is_first":false,"is_join_receiver":false,"is_naming":false,"is_special_batch":0,"magnification":1.2,"medal_info":{"anchor_roomid":0,"anchor_uname":"","guard_level":0,"icon_id":0,"is_lighted":1,"medal_color":9272486,"medal_color_border":9272486,"medal_color_end":9272486,"medal_color_start":9272486,"medal_level":10,"medal_name":"正鲸人","special":"","target_id":1398337493},"name_color":"","num":1,"original_gift_name":"","price":100,"rcost":5240877,"receive_user_info":{"uid":1398337493,"uname":"鲸鱼娘西丝特official"},"remain":0,"rnd":"1674826549121000002","send_master":null,"silver":0,"super":0,"super_batch_gift_num":67,"super_gift_num":67,"svga_block":0,"switch":true,"tag_image":"","tid":"1674826549121000002","timestamp":1674826549,"top_list":null,"total_coin":100,"uid":351171220,"uname":"OUO-13"}},{"cmd":"DANMU_MSG","info":[[0,1,25,16777215,1674826549232,1407599395,0,"6c11c479",0,0,0,"",0,"{}","{}",{"mode":0,"show_player_type":0,"extra":"{\"send_from_me\":false,\"mode\":0,\"color\":16777215,\"dm_type\":0,\"font_size\":25,\"player_mode\":1,\"show_player_type\":0,\"content\":\"提督房管吧\",\"user_hash\":\"1813103737\",\"emoticon_unique\":\"\",\"bulge_display\":0,\"recommend_score\":5,\"main_state_dm_color\":\"\",\"objective_state_dm_color\":\"\",\"direction\":0,\"pk_direction\":0,\"quartet_direction\":0,\"anniversary_crowd\":0,\"yeah_space_type\":\"\",\"yeah_space_url\":\"\",\"jump_to_url\":\"\",\"space_type\":\"\",\"space_url\":\"\",\"animation\":{},\"emots\":null}"},{"activity_identity":"","activity_source":0,"not_show":0}],"提督房管吧",[347432355,"只是闻人",0,0,0,10000,1,""],[5,"粉丝团","崩坏3第一偶像爱酱",1319882,6126494,"",0,12632256,12632256,12632256,0,0,27534330],[0,0,9868950,">50000",0],["",""],0,0,null,{"ts":1674826549,"ct":"442B0DAE"},0,0,null,null,0,21]},{"cmd":"SEND_GIFT","data":{"action":"投喂","batch_combo_id":"","batch_combo_send":null,"beatId":"","biz_source":"Live","blind_gift":null,"broadcast_id":0,"coin_type":"silver","combo_resources_id":1,"combo_send":null,"combo_stay_time":3,"combo_total_coin":0,"crit_prob":0,"demarcation":1,"discount_price":0,"dmscore":4,"draw":0,"effect":0,"effect_block":1,"face":"https://i1.hdslb.com/bfs/face/d615ea19a3bab1bec5df3a50d477bf4a08ef9671.jpg","face_effect_id":0,"face_effect_type":0,"float_sc_resource_id":0,"giftId":1,"giftName":"辣条","giftType":5,"gold":0,"guard_level":0,"is_first":true,"is_join_receiver":false,"is_naming":false,"is_special_batch":0,"magnification":1,"medal_info":{"anchor_roomid":0,"anchor_uname":"","guard_level":0,"icon_id":0,"is_lighted":0,"medal_color":0,"medal_color_border":0,"medal_color_end":0,"medal_color_start":0,"medal_level":0,"medal_name":"","special":"","target_id":0},"name_color":"","num":1,"original_gift_name":"","price":100,"rcost":5240877,"receive_user_info":{"uid":1398337493,"uname":"鲸鱼娘西丝特official"},"remain":0,"rnd":"1674826549120300003","send_master":null,"silver":0,"super":0,"super_batch_gift_num":0,"super_gift_num":0,"svga_block":0,"switch":true,"tag_image":"","tid":"1674826549120300003","timestamp":1674826549,"top_list":null,"total_coin":100,"uid":3493091801565823,"uname":"-露桑-"}},{"cmd":"SEND_GIFT","data":{"action":"投喂","batch_combo_id":"","batch_combo_send":null,"beatId":"","biz_source":"live","blind_gift":null,"broadcast_id":0,"coin_type":"silver","combo_resources_id":1,"combo_send":null,"combo_stay_time":3,"combo_total_coin":0,"crit_prob":0,"demarcation":1,"discount_price":0,"dmscore":4,"draw":0,"effect":0,"effect_block":1,"face":"https://i2.hdslb.com/bfs/face/2a173dd01e148ff95efda9a03520ba553c19dc28.jpg","face_effect_id":0,"face_effect_type":0,"float_sc_resource_id":0,"giftId":1,"giftName":"辣条","giftType":5,"gold":0,"guard_level":0,"is_first":true,"is_join_receiver":false,"is_naming":false,"is_special_batch":0,"magnification":1,"medal_info":{"anchor_roomid":0,"anchor_uname":"","guard_level":0,"icon_id":0,"is_lighted":0,"medal_color":0,"medal_color_border":0,"medal_color_end":0,"medal_color_start":0,"medal_level":0,"medal_name":"","special":"","target_id":0},"name_color":"","num":1,"original_gift_name":"","price":100,"rcost":5240877,"receive_user_info":{"uid":1398337493,"uname":"鲸鱼娘西丝特official"},"remain":0,"rnd":"1674826549120700001","send_master":null,"silver":0,"super":0,"super_batch_gift_num":0,"super_gift_num":0,"svga_block":0,"switch":true,"tag_image":"","tid":"1674826549120700001","timestamp":1674826549,"top_list":null,"total_coin":100,"uid":75513887,"uname":"陈謀"}},{"cmd":"SEND_GIFT","data":{"action":"投喂","batch_combo_id":"","batch_combo_send":null,"beatId":"","biz_source":"live","blind_gift":null,"broadcast_id":0,"coin_type":"silver","combo_resources_id":1,"combo_send":null,"combo_stay_time":3,"combo_total_coin":0,"crit_prob":0,"demarcation":1,"discount_price":0,"dmscore":16,"draw":0,"effect":0,"effect_block":1,"face":"https://i2.hdslb.com/bfs/face/e030fdf9ea36004d7cfee635347245e5bff16695.jpg","face_effect_id":0,"face_effect_type":0,"float_sc_resource_id":0,"giftId":1,"giftName":"辣条","giftType":5,"gold":0,"guard_level":0,"is_first":true,"is_join_receiver":false,"is_naming":false,"is_special_batch":0,"magnification":1,"medal_info":{"anchor_roomid":0,"anchor_uname":"","guard_level":0,"icon_id":0,"is_lighted":1,"medal_color":6067854,"medal_color_border":6067854,"medal_color_end":6067854,"medal_color_start":6067854,"medal_level":3,"medal_name":"正鲸人","special":"","target_id":1398337493},"name_color":"","num":1,"original_gift_name":"","price":100,"rcost":5240877,"receive_user_info":{"uid":1398337493,"uname":"鲸鱼娘西丝特official"},"remain":0,"rnd":"1674826549120500003","send_master":null,"silver":0,"super":0,"super_batch_gift_num":0,"super_gift_num":0,"svga_block":0,"switch":true,"tag_image":"","tid":"1674826549120500003","timestamp":1674826549,"top_list":null,"total_coin":100,"uid":695089025,"uname":"恂w"}},{"cmd":"SEND_GIFT","data":{"action":"投喂","batch_combo_id":"batch:gift:combo_id:438090148:1398337493:32590:1674826547.6790","batch_combo_send":null,"beatId":"","biz_source":"live","blind_gift":null,"broadcast_id":0,"coin_type":"gold","combo_resources_id":1,"combo_send":null,"combo_stay_time":3,"combo_total_coin":500,"crit_prob":0,"demarcation":1,"discount_price":100,"dmscore":8,"draw":0,"effect":0,"effect_block":0,"face":"https://i1.hdslb.com/bfs/face/61b1be67f49972ffc711714cc40540389922157f.jpg","face_effect_id":0,"face_effect_type":0,"float_sc_resource_id":0,"giftId":32590,"giftName":"团圆扇","giftType":0,"gold":0,"guard_level":0,"is_first":false,"is_join_receiver":false,"is_naming":false,"is_special_batch":0,"magnification":1,"medal_info":{"anchor_roomid":0,"anchor_uname":"","guard_level":0,"icon_id":0,"is_lighted":0,"medal_color":0,"medal_color_border":0,"medal_color_end":0,"medal_color_start":0,"medal_level":0,"medal_name":"","special":"","target_id":0},"name_color":"","num":1,"original_gift_name":"","price":100,"rcost":5240877,"receive_user_info":{"uid":1398337493,"uname":"鲸鱼娘西丝特official"},"remain":0,"rnd":"1674826549121800002","send_master":null,"silver":0,"super":0,"super_batch_gift_num":5,"super_gift_num":5,"svga_block":0,"switch":true,"tag_image":"","tid":"1674826549121800002","timestamp":1674826549,"top_list":null,"total_coin":100,"uid":438090148,"uname":"东方大弥超可爱"}},{"cmd":"SEND_GIFT","data":{"action":"投喂","batch_combo_id":"","batch_combo_send":null,"beatId":"","biz_source":"live","blind_gift":null,"broadcast_id":0,"coin_type":"silver","combo_resources_id":1,"combo_send":null,"combo_stay_time":3,"combo_total_coin":0,"crit_prob":0,"demarcation":1,"discount_price":0,"dmscore":16,"draw":0,"effect":0,"effect_block":1,"face":"https://i1.hdslb.com/bfs/face/487ab8c1bd6c0aadb7e275aed02d0945f80db6b1.jpg","face_effect_id":0,"face_effect_type":0,"float_sc_resource_id":0,"giftId":1,"giftName":"辣条","giftType":5,"gold":0,"guard_level":0,"is_first":true,"is_join_receiver":false,"is_naming":false,"is_special_batch":0,"magnification":1,"medal_info":{"anchor_roomid":0,"anchor_uname":"","guard_level":0,"icon_id":0,"is_lighted":1,"medal_color":6067854,"medal_color_border":6067854,"medal_color_end":6067854,"medal_color_start":6067854,"medal_level":4,"medal_name":"正鲸人","special":"","target_id":1398337493},"name_color":"","num":1,"original_gift_name":"","price":100,"rcost":5240877,"receive_user_info":{"uid":1398337493,"uname":"鲸鱼娘西丝特official"},"remain":0,"rnd":"1674826549120000002","send_master":null,"silver":0,"super":0,"super_batch_gift_num":0,"super_gift_num":0,"svga_block":0,"switch":true,"tag_image":"","tid":"1674826549120000002","timestamp":1674826549,"top_list":null,"total_coin":100,"uid":349152160,"uname":"WEAK_GOD"}},{"cmd":"SEND_GIFT","data":{"action":"投喂","batch_combo_id":"batch:gift:combo_id:351171220:1398337493:32345:1674826535.8373","batch_combo_send":null,"beatId":"","biz_source":"live","blind_gift":null,"broadcast_id":0,"coin_type":"gold","combo_resources_id":1,"combo_send":null,"combo_stay_time":3,"combo_total_coin":6800,"crit_prob":0,"demarcation":1,"discount_price":100,"dmscore":56,"draw":0,"effect":0,"effect_block":0,"face":"https://i1.hdslb.com/bfs/face/0b5c367a3a04e3d431529db6b8f2d63e113c251a.jpg","face_effect_id":0,"face_effect_type":0,"float_sc_resource_id":0,"giftId":32345,"giftName":"人气票","giftType":0,"gold":0,"guard_level":0,"is_first":false,"is_join_receiver":false,"is_naming":false,"is_special_batch":0,"magnification":1.2,"medal_info":{"anchor_roomid":0,"anchor_uname":"","guard_level":0,"icon_id":0,"is_lighted":1,"medal_color":9272486,"medal_color_border":9272486,"medal_color_end":9272486,"medal_color_start":9272486,"medal_level":10,"medal_name":"正鲸人","special":"","target_id":1398337493},"name_color":"","num":1,"original_gift_name":"","price":100,"rcost":5240877,"receive_user_info":{"uid":1398337493,"uname":"鲸鱼娘西丝特official"},"remain":0,"rnd":"1674826549121000004","send_master":null,"silver":0,"super":0,"super_batch_gift_num":68,"super_gift_num":68,"svga_block":0,"switch":true,"tag_image":"","tid":"1674826549121000004","timestamp":1674826549,"top_list":null,"total_coin":100,"uid":351171220,"uname":"OUO-13"}},{"cmd":"DANMU_MSG","info":[[0,1,25,16777215,1674826549366,-663972003,0,"a09840e1",0,0,0,"",0,"{}","{}",{"mode":0,"show_player_type":0,"extra":"{\"send_from_me\":false,\"mode\":0,\"color\":16777215,\"dm_type\":0,\"font_size\":25,\"player_mode\":1,\"show_player_type\":0,\"content\":\"可以制作东西\",\"user_hash\":\"2694332641\",\"emoticon_unique\":\"\",\"bulge_display\":0,\"recommend_score\":0,\"main_state_dm_color\":\"\",\"objective_state_dm_color\":\"\",\"direction\":0,\"pk_direction\":0,\"quartet_direction\":0,\"anniversary_crowd\":0,\"yeah_space_type\":\"\",\"yeah_space_url\":\"\",\"jump_to_url\":\"\",\"space_type\":\"\",\"space_url\":\"\",\"animation\":{},\"emots\":null}"},{"activity_identity":"","activity_source":0,"not_show":0}],"可以制作东西",[37637561,"冰天丫",0,0,0,10000,1,""],[23,"韬女鹅","文韬Stefan",21996307,1725515,"",0,6809855,1725515,5414290,3,1,412504829],[19,0,6406234,">50000",0],["",""],0,0,null,{"ts":1674826549,"ct":"8D63B4EB"},0,0,null,null,0,70]},{"cmd":"SEND_GIFT","data":{"action":"投喂","batch_combo_id":"batch:gift:combo_id:670973560:1398337493:30869:1674826545.9590","batch_combo_send":null,"beatId":"","biz_source":"live","blind_gift":null,"broadcast_id":0,"coin_type":"gold","combo_resources_id":1,"combo_send":null,"combo_stay_time":3,"combo_total_coin":500,"crit_prob":0,"demarcation":1,"discount_price":100,"dmscore":56,"draw":0,"effect":0,"effect_block":0,"face":"https://i1.hdslb.com/bfs/face/05685ff6010639605b1fff93c4d8b531f1d16bb2.jpg","face_effect_id":0,"face_effect_type":0,"float_sc_resource_id":0,"giftId":30869,"giftName":"心动卡","giftType":0,"gold":0,"guard_level":0,"is_first":false,"is_join_receiver":false,"is_naming":false,"is_special_batch":0,"magnification":1,"medal_info":{"anchor_roomid":0,"anchor_uname":"","guard_level":0,"icon_id":0,"is_lighted":1,"medal_color":9272486,"medal_color_border":9272486,"medal_color_end":9272486,"medal_color_start":9272486,"medal_level":10,"medal_name":"正鲸人","special":"","target_id":1398337493},"name_color":"","num":1,"original_gift_name":"","price":100,"rcost":5240877,"receive_user_info":{"uid":1398337493,"uname":"鲸鱼娘西丝特official"},"remain":0,"rnd":"1674826549131000003","send_master":null,"silver":0,"super":0,"super_batch_gift_num":5,"super_gift_num":5,"svga_block":0,"switch":true,"tag_image":"","tid":"1674826549131000003","timestamp":1674826549,"top_list":null,"total_coin":100,"uid":670973560,"uname":"有在记着冉冉"}},{"cmd":"SEND_GIFT","data":{"action":"投喂","batch_combo_id":"","batch_combo_send":null,"beatId":"","biz_source":"Live","blind_gift":null,"broadcast_id":0,"coin_type":"silver","combo_resources_id":1,"combo_send":null,"combo_stay_time":3,"combo_total_coin":0,"crit_prob":0,"demarcation":1,"discount_price":0,"dmscore":4,"draw":0,"effect":0,"effect_block":1,"face":"https://i1.hdslb.com/bfs/face/d615ea19a3bab1bec5df3a50d477bf4a08ef9671.jpg","face_effect_id":0,"face_effect_type":0,"float_sc_resource_id":0,"giftId":1,"giftName":"辣条","giftType":5,"gold":0,"guard_level":0,"is_first":true,"is_join_receiver":false,"is_naming":false,"is_special_batch":0,"magnification":1,"medal_info":{"anchor_roomid":0,"anchor_uname":"","guard_level":0,"icon_id":0,"is_lighted":0,"medal_color":0,"medal_color_border":0,"medal_color_end":0,"medal_color_start":0,"medal_level":0,"medal_name":"","special":"","target_id":0},"name_color":"","num":1,"original_gift_name":"","price":100,"rcost":5240877,"receive_user_info":{"uid":1398337493,"uname":"鲸鱼娘西丝特official"},"remain":0,"rnd":"1674826549120300004","send_master":null,"silver":0,"super":0,"super_batch_gift_num":0,"super_gift_num":0,"svga_block":0,"switch":true,"tag_image":"","tid":"1674826549120300004","timestamp":1674826549,"top_list":null,"total_coin":100,"uid":3493091801565823,"uname":"-露桑-"}},{"cmd":"DANMU_MSG","info":[[0,1,25,16777215,1674826549465,183854556,0,"22a61104",0,0,0,"",0,"{}","{}",{"mode":0,"show_player_type":0,"extra":"{\"send_from_me\":false,\"mode\":0,\"color\":16777215,\"dm_type\":0,\"font_size\":25,\"player_mode\":1,\"show_player_type\":0,\"content\":\"西门\",\"user_hash\":\"581308676\",\"emoticon_unique\":\"\",\"bulge_display\":0,\"recommend_score\":5,\"main_state_dm_color\":\"\",\"objective_state_dm_color\":\"\",\"direction\":0,\"pk_direction\":0,\"quartet_direction\":0,\"anniversary_crowd\":0,\"yeah_space_type\":\"\",\"yeah_space_url\":\"\",\"jump_to_url\":\"\",\"space_type\":\"\",\"space_url\":\"\",\"animation\":{},\"emots\":null}"},{"activity_identity":"","activity_source":0,"not_show":0}],"西门",[1210103516,"豆见",0,0,0,10000,1,""],[],[0,0,9868950,">50000",0],["",""],0,0,null,{"ts":1674826549,"ct":"C717BEAC"},0,0,null,null,0,7]},{"cmd":"SEND_GIFT","data":{"action":"投喂","batch_combo_id":"","batch_combo_send":null,"beatId":"","biz_source":"live","blind_gift":null,"broadcast_id":0,"coin_type":"silver","combo_resources_id":1,"combo_send":null,"combo_stay_time":3,"combo_total_coin":0,"crit_prob":0,"demarcation":1,"discount_price":0,"dmscore":60,"draw":0,"effect":0,"effect_block":1,"face":"https://i1.hdslb.com/bfs/face/321cea79c09fc9ec8d5ed16dcb3ecba0904518f9.jpg","face_effect_id":0,"face_effect_type":0,"float_sc_resource_id":0,"giftId":31531,"giftName":"PK票","giftType":5,"gold":0,"guard_level":0,"is_first":true,"is_join_receiver":false,"is_naming":false,"is_special_batch":0,"magnification":1,"medal_info":{"anchor_roomid":0,"anchor_uname":"","guard_level":3,"icon_id":0,"is_lighted":1,"medal_color":1725515,"medal_color_border":6809855,"medal_color_end":5414290,"medal_color_start":1725515,"medal_level":21,"medal_name":"正鲸人","special":"","target_id":1398337493},"name_color":"","num":1,"original_gift_name":"","price":0,"rcost":5240876,"receive_user_info":{"uid":1398337493,"uname":"鲸鱼娘西丝特official"},"remain":0,"rnd":"1674826549120400001","send_master":null,"silver":0,"super":0,"super_batch_gift_num":0,"super_gift_num":0,"svga_block":0,"switch":true,"tag_image":"","tid":"1674826549120400001","timestamp":1674826549,"top_list":null,"total_coin":0,"uid":347204764,"uname":"苏布奇"}},{"cmd":"SEND_GIFT","data":{"action":"投喂","batch_combo_id":"","batch_combo_send":null,"beatId":"","biz_source":"live","blind_gift":null,"broadcast_id":0,"coin_type":"silver","combo_resources_id":1,"combo_send":null,"combo_stay_time":3,"combo_total_coin":0,"crit_prob":0,"demarcation":1,"discount_price":0,"dmscore":4,"draw":0,"effect":0,"effect_block":1,"face":"https://i2.hdslb.com/bfs/face/2a173dd01e148ff95efda9a03520ba553c19dc28.jpg","face_effect_id":0,"face_effect_type":0,"float_sc_resource_id":0,"giftId":1,"giftName":"辣条","giftType":5,"gold":0,"guard_level":0,"is_first":true,"is_join_receiver":false,"is_naming":false,"is_special_batch":0,"magnification":1,"medal_info":{"anchor_roomid":0,"anchor_uname":"","guard_level":0,"icon_id":0,"is_lighted":0,"medal_color":0,"medal_color_border":0,"medal_color_end":0,"medal_color_start":0,"medal_level":0,"medal_name":"","special":"","target_id":0},"name_color":"","num":1,"original_gift_name":"","price":100,"rcost":5240877,"receive_user_info":{"uid":1398337493,"uname":"鲸鱼娘西丝特official"},"remain":0,"rnd":"1674826549120700004","send_master":null,"silver":0,"super":0,"super_batch_gift_num":0,"super_gift_num":0,"svga_block":0,"switch":true,"tag_image":"","tid":"1674826549120700004","timestamp":1674826549,"top_list":null,"total_coin":100,"uid":75513887,"uname":"陈謀"}},{"cmd":"SEND_GIFT","data":{"action":"投喂","batch_combo_id":"","batch_combo_send":null,"beatId":"","biz_source":"live","blind_gift":null,"broadcast_id":0,"coin_type":"silver","combo_resources_id":1,"combo_send":null,"combo_stay_time":3,"combo_total_coin":0,"crit_prob":0,"demarcation":1,"discount_price":0,"dmscore":20,"draw":0,"effect":0,"effect_block":1,"face":"https://i0.hdslb.com/bfs/face/17cd2a536a5e9477c239f78865da8a6f0c5dace5.jpg","face_effect_id":0,"face_effect_type":0,"float_sc_resource_id":0,"giftId":1,"giftName":"辣条","giftType":5,"gold":0,"guard_level":0,"is_first":true,"is_join_receiver":false,"is_naming":false,"is_special_batch":0,"magnification":1,"medal_info":{"anchor_roomid":0,"anchor_uname":"","guard_level":0,"icon_id":0,"is_lighted":1,"medal_color":9272486,"medal_color_border":9272486,"medal_color_end":9272486,"medal_color_start":9272486,"medal_level":9,"medal_name":"正鲸人","special":"","target_id":1398337493},"name_color":"","num":1,"original_gift_name":"","price":100,"rcost":5240877,"receive_user_info":{"uid":1398337493,"uname":"鲸鱼娘西丝特official"},"remain":0,"rnd":"1674826549120200002","send_master":null,"silver":0,"super":0,"super_batch_gift_num":0,"super_gift_num":0,"svga_block":0,"switch":true,"tag_image":"","tid":"1674826549120200002","timestamp":1674826549,"top_list":null,"total_coin":100,"uid":1657528572,"uname":"萝莉保护协会-官方"}},{"cmd":"SEND_GIFT","data":{"action":"投喂","batch_combo_id":"","batch_combo_send":null,"beatId":"","biz_source":"live","blind_gift":null,"broadcast_id":0,"coin_type":"silver","combo_resources_id":1,"combo_send":null,"combo_stay_time":3,"combo_total_coin":0,"crit_prob":0,"demarcation":1,"discount_price":0,"dmscore":20,"draw":0,"effect":0,"effect_block":1,"face":"https://i0.hdslb.com/bfs/face/17cd2a536a5e9477c239f78865da8a6f0c5dace5.jpg","face_effect_id":0,"face_effect_type":0,"float_sc_resource_id":0,"giftId":1,"giftName":"辣条","giftType":5,"gold":0,"guard_level":0,"is_first":true,"is_join_receiver":false,"is_naming":false,"is_special_batch":0,"magnification":1,"medal_info":{"anchor_roomid":0,"anchor_uname":"","guard_level":0,"icon_id":0,"is_lighted":1,"medal_color":9272486,"medal_color_border":9272486,"medal_color_end":9272486,"medal_color_start":9272486,"medal_level":9,"medal_name":"正鲸人","special":"","target_id":1398337493},"name_color":"","num":1,"original_gift_name":"","price":100,"rcost":5240877,"receive_user_info":{"uid":1398337493,"uname":"鲸鱼娘西丝特official"},"remain":0,"rnd":"1674826549120200003","send_master":null,"silver":0,"super":0,"super_batch_gift_num":0,"super_gift_num":0,"svga_block":0,"switch":true,"tag_image":"","tid":"1674826549120200003","timestamp":1674826549,"top_list":null,"total_coin":100,"uid":1657528572,"uname":"萝莉保护协会-官方"}},{"cmd":"SEND_GIFT","data":{"action":"投喂","batch_combo_id":"","batch_combo_send":null,"beatId":"","biz_source":"Live","blind_gift":null,"broadcast_id":0,"coin_type":"silver","combo_resources_id":1,"combo_send":null,"combo_stay_time":3,"combo_total_coin":0,"crit_prob":0,"demarcation":1,"discount_price":0,"dmscore":4,"draw":0,"effect":0,"effect_block":1,"face":"https://i1.hdslb.com/bfs/face/d615ea19a3bab1bec5df3a50d477bf4a08ef9671.jpg","face_effect_id":0,"face_effect_type":0,"float_sc_resource_id":0,"giftId":1,"giftName":"辣条","giftType":5,"gold":0,"guard_level":0,"is_first":true,"is_join_receiver":false,"is_naming":false,"is_special_batch":0,"magnification":1,"medal_info":{"anchor_roomid":0,"anchor_uname":"","guard_level":0,"icon_id":0,"is_lighted":0,"medal_color":0,"medal_color_border":0,"medal_color_end":0,"medal_color_start":0,"medal_level":0,"medal_name":"","special":"","target_id":0},"name_color":"","num":1,"original_gift_name":"","price":100,"rcost":5240877,"receive_user_info":{"uid":1398337493,"uname":"鲸鱼娘西丝特official"},"remain":0,"rnd":"1674826549120300007","send_master":null,"silver":0,"super":0,"super_batch_gift_num":0,"super_gift_num":0,"svga_block":0,"switch":true,"tag_image":"","tid":"1674826549120300007","timestamp":1674826549,"top_list":null,"total_coin":100,"uid":3493091801565823,"uname":"-露桑-"}},{"cmd":"SEND_GIFT","data":{"action":"投喂","batch_combo_id":"","batch_combo_send":null,"beatId":"","biz_source":"live","blind_gift":null,"broadcast_id":0,"coin_type":"silver","combo_resources_id":1,"combo_send":null,"combo_stay_time":3,"combo_total_coin":0,"crit_prob":0,"demarcation":1,"discount_price":0,"dmscore":20,"draw":0,"effect":0,"effect_block":1,"face":"https://i0.hdslb.com/bfs/face/17cd2a536a5e9477c239f78865da8a6f0c5dace5.jpg","face_effect_id":0,"face_effect_type":0,"float_sc_resource_id":0,"giftId":1,"giftName":"辣条","giftType":5,"gold":0,"guard_level":0,"is_first":true,"is_join_receiver":false,"is_naming":false,"is_special_batch":0,"magnification":1,"medal_info":{"anchor_roomid":0,"anchor_uname":"","guard_level":0,"icon_id":0,"is_lighted":1,"medal_color":9272486,"medal_color_border":9272486,"medal_color_end":9272486,"medal_color_start":9272486,"medal_level":9,"medal_name":"正鲸人","special":"","target_id":1398337493},"name_color":"","num":1,"original_gift_name":"","price":100,"rcost":5240877,"receive_user_info":{"uid":1398337493,"uname":"鲸鱼娘西丝特official"},"remain":0,"rnd":"1674826549120200004","send_master":null,"silver":0,"super":0,"super_batch_gift_num":0,"super_gift_num":0,"svga_block":0,"switch":true,"tag_image":"","tid":"1674826549120200004","timestamp":1674826549,"top_list":null,"total_coin":100,"uid":1657528572,"uname":"萝莉保护协会-官方"}},{"cmd":"DANMU_MSG","info":[[0,1,25,16777215,1674826549579,1969940526,0,"30883e32",0,0,0,"",0,"{}","{}",{"mode":0,"show_player_type":0,"extra":"{\"send_from_me\":false,\"mode\":0,\"color\":16777215,\"dm_type\":0,\"font_size\":25,\"player_mode\":1,\"show_player_type\":0,\"content\":\"西门\",\"user_hash\":\"814235186\",\"emoticon_unique\":\"\",\"bulge_display\":0,\"recommend_score\":0,\"main_state_dm_color\":\"\",\"objective_state_dm_color\":\"\",\"direction\":0,\"pk_direction\":0,\"quartet_direction\":0,\"anniversary_crowd\":0,\"yeah_space_type\":\"\",\"yeah_space_url\":\"\",\"jump_to_url\":\"\",\"space_type\":\"\",\"space_url\":\"\",\"animation\":{},\"emots\":null}"},{"activity_identity":"","activity_source":0,"not_show":0}],"西门",[426213125,"日暮nightfall",0,0,0,10000,1,""],[5,"拼溪溪","两只沈梦溪",21841810,6126494,"",0,12632256,12632256,12632256,0,0,340273654],[0,0,9868950,">50000",0],["",""],0,0,null,{"ts":1674826549,"ct":"6CD8455E"},0,0,null,null,0,21]},{"cmd":"SEND_GIFT","data":{"action":"投喂","batch_combo_id":"","batch_combo_send":null,"beatId":"","biz_source":"live","blind_gift":null,"broadcast_id":0,"coin_type":"silver","combo_resources_id":1,"combo_send":null,"combo_stay_time":3,"combo_total_coin":0,"crit_prob":0,"demarcation":1,"discount_price":0,"dmscore":16,"draw":0,"effect":0,"effect_block":1,"face":"https://i1.hdslb.com/bfs/face/487ab8c1bd6c0aadb7e275aed02d0945f80db6b1.jpg","face_effect_id":0,"face_effect_type":0,"float_sc_resource_id":0,"giftId":1,"giftName":"辣条","giftType":5,"gold":0,"guard_level":0,"is_first":true,"is_join_receiver":false,"is_naming":false,"is_special_batch":0,"magnification":1,"medal_info":{"anchor_roomid":0,"anchor_uname":"","guard_level":0,"icon_id":0,"is_lighted":1,"medal_color":6067854,"medal_color_border":6067854,"medal_color_end":6067854,"medal_color_start":6067854,"medal_level":4,"medal_name":"正鲸人","special":"","target_id":1398337493},"name_color":"","num":1,"original_gift_name":"","price":100,"rcost":5240877,"receive_user_info":{"uid":1398337493,"uname":"鲸鱼娘西丝特official"},"remain":0,"rnd":"1674826549120000003","send_master":null,"silver":0,"super":0,"super_batch_gift_num":0,"super_gift_num":0,"svga_block":0,"switch":true,"tag_image":"","tid":"1674826549120000003","timestamp":1674826549,"top_list":null,"total_coin":100,"uid":349152160,"uname":"WEAK_GOD"}},{"cmd":"DANMU_MSG","info":[[0,4,25,14893055,1674826549656,-2072962152,0,"16217ac7",0,0,5,"#1453BAFF,#4C2263A2,#3353BAFF",0,"{}","{}",{"mode":0,"show_player_type":0,"extra":"{\"send_from_me\":false,\"mode\":0,\"color\":14893055,\"dm_type\":0,\"font_size\":25,\"player_mode\":4,\"show_player_type\":0,\"content\":\"黄毛……\",\"user_hash\":\"371292871\",\"emoticon_unique\":\"\",\"bulge_display\":0,\"recommend_score\":1,\"main_state_dm_color\":\"\",\"objective_state_dm_color\":\"\",\"direction\":0,\"pk_direction\":0,\"quartet_direction\":0,\"anniversary_crowd\":0,\"yeah_space_type\":\"\",\"yeah_space_url\":\"\",\"jump_to_url\":\"\",\"space_type\":\"\",\"space_url\":\"\",\"animation\":{},\"emots\":null}"},{"activity_identity":"","activity_source":0,"not_show":0}],"黄毛……",[264899543,"阿斯托尔福的master_",0,0,0,10000,1,"#00D1F1"],[21,"正鲸人","鲸鱼娘西丝特official",26545331,1725515,"",0,6809855,1725515,5414290,3,1,1398337493],[11,0,6406234,">50000",0],["",""],0,3,null,{"ts":1674826549,"ct":"EE5FC1B5"},0,0,null,null,0,105]},{"cmd":"SEND_GIFT","data":{"action":"投喂","batch_combo_id":"","batch_combo_send":null,"beatId":"","biz_source":"live","blind_gift":null,"broadcast_id":0,"coin_type":"silver","combo_resources_id":1,"combo_send":null,"combo_stay_time":3,"combo_total_coin":0,"crit_prob":0,"demarcation":1,"discount_price":0,"dmscore":20,"draw":0,"effect":0,"effect_block":1,"face":"https://i0.hdslb.com/bfs/face/17cd2a536a5e9477c239f78865da8a6f0c5dace5.jpg","face_effect_id":0,"face_effect_type":0,"float_sc_resource_id":0,"giftId":1,"giftName":"辣条","giftType":5,"gold":0,"guard_level":0,"is_first":true,"is_join_receiver":false,"is_naming":false,"is_special_batch":0,"magnification":1,"medal_info":{"anchor_roomid":0,"anchor_uname":"","guard_level":0,"icon_id":0,"is_lighted":1,"medal_color":9272486,"medal_color_border":9272486,"medal_color_end":9272486,"medal_color_start":9272486,"medal_level":9,"medal_name":"正鲸人","special":"","target_id":1398337493},"name_color":"","num":1,"original_gift_name":"","price":100,"rcost":5240877,"receive_user_info":{"uid":1398337493,"uname":"鲸鱼娘西丝特official"},"remain":0,"rnd":"1674826549120200005","send_master":null,"silver":0,"super":0,"super_batch_gift_num":0,"super_gift_num":0,"svga_block":0,"switch":true,"tag_image":"","tid":"1674826549120200005","timestamp":1674826549,"top_list":null,"total_coin":100,"uid":1657528572,"uname":"萝莉保护协会-官方"}},{"cmd":"SEND_GIFT","data":{"action":"投喂","batch_combo_id":"","batch_combo_send":null,"beatId":"","biz_source":"live","blind_gift":null,"broadcast_id":0,"coin_type":"silver","combo_resources_id":1,"combo_send":null,"combo_stay_time":3,"combo_total_coin":0,"crit_prob":0,"demarcation":1,"discount_price":0,"dmscore":16,"draw":0,"effect":0,"effect_block":1,"face":"https://i2.hdslb.com/bfs/face/e030fdf9ea36004d7cfee635347245e5bff16695.jpg","face_effect_id":0,"face_effect_type":0,"float_sc_resource_id":0,"giftId":1,"giftName":"辣条","giftType":5,"gold":0,"guard_level":0,"is_first":true,"is_join_receiver":false,"is_naming":false,"is_special_batch":0,"magnification":1,"medal_info":{"anchor_roomid":0,"anchor_uname":"","guard_level":0,"icon_id":0,"is_lighted":1,"medal_color":6067854,"medal_color_border":6067854,"medal_color_end":6067854,"medal_color_start":6067854,"medal_level":3,"medal_name":"正鲸人","special":"","target_id":1398337493},"name_color":"","num":1,"original_gift_name":"","price":100,"rcost":5240877,"receive_user_info":{"uid":1398337493,"uname":"鲸鱼娘西丝特official"},"remain":0,"rnd":"1674826549120500007","send_master":null,"silver":0,"super":0,"super_batch_gift_num":0,"super_gift_num":0,"svga_block":0,"switch":true,"tag_image":"","tid":"1674826549120500007","timestamp":1674826549,"top_list":null,"total_coin":100,"uid":695089025,"uname":"恂w"}},{"cmd":"SEND_GIFT","data":{"action":"投喂","batch_combo_id":"batch:gift:combo_id:351171220:1398337493:32345:1674826535.8373","batch_combo_send":null,"beatId":"","biz_source":"live","blind_gift":null,"broadcast_id":0,"coin_type":"gold","combo_resources_id":1,"combo_send":null,"combo_stay_time":3,"combo_total_coin":6900,"crit_prob":0,"demarcation":1,"discount_price":100,"dmscore":56,"draw":0,"effect":0,"effect_block":0,"face":"https://i1.hdslb.com/bfs/face/0b5c367a3a04e3d431529db6b8f2d63e113c251a.jpg","face_effect_id":0,"face_effect_type":0,"float_sc_resource_id":0,"giftId":32345,"giftName":"人气票","giftType":0,"gold":0,"guard_level":0,"is_first":false,"is_join_receiver":false,"is_naming":false,"is_special_batch":0,"magnification":1.2,"medal_info":{"anchor_roomid":0,"anchor_uname":"","guard_level":0,"icon_id":0,"is_lighted":1,"medal_color":9272486,"medal_color_border":9272486,"medal_color_end":9272486,"medal_color_start":9272486,"medal_level":10,"medal_name":"正鲸人","special":"","target_id":1398337493},"name_color":"","num":1,"original_gift_name":"","price":100,"rcost":5240877,"receive_user_info":{"uid":1398337493,"uname":"鲸鱼娘西丝特official"},"remain":0,"rnd":"1674826549121000007","send_master":null,"silver":0,"super":0,"super_batch_gift_num":69,"super_gift_num":69,"svga_block":0,"switch":true,"tag_image":"","tid":"1674826549121000007","timestamp":1674826549,"top_list":null,"total_coin":100,"uid":351171220,"uname":"OUO-13"}},{"cmd":"SEND_GIFT","data":{"action":"投喂","batch_combo_id":"","batch_combo_send":null,"beatId":"","biz_source":"live","blind_gift":null,"broadcast_id":0,"coin_type":"silver","combo_resources_id":1,"combo_send":null,"combo_stay_time":3,"combo_total_coin":0,"crit_prob":0,"demarcation":1,"discount_price":0,"dmscore":4,"draw":0,"effect":0,"effect_block":1,"face":"https://i2.hdslb.com/bfs/face/2a173dd01e148ff95efda9a03520ba553c19dc28.jpg","face_effect_id":0,"face_effect_type":0,"float_sc_resource_id":0,"giftId":1,"giftName":"辣条","giftType":5,"gold":0,"guard_level":0,"is_first":true,"is_join_receiver":false,"is_naming":false,"is_special_batch":0,"magnification":1,"medal_info":{"anchor_roomid":0,"anchor_uname":"","guard_level":0,"icon_id":0,"is_lighted":0,"medal_color":0,"medal_color_border":0,"medal_color_end":0,"medal_color_start":0,"medal_level":0,"medal_name":"","special":"","target_id":0},"name_color":"","num":1,"original_gift_name":"","price":100,"rcost":5240877,"receive_user_info":{"uid":1398337493,"uname":"鲸鱼娘西丝特official"},"remain":0,"rnd":"1674826549120700009","send_master":null,"silver":0,"super":0,"super_batch_gift_num":0,"super_gift_num":0,"svga_block":0,"switch":true,"tag_image":"","tid":"1674826549120700009","timestamp":1674826549,"top_list":null,"total_coin":100,"uid":75513887,"uname":"陈謀"}},{"cmd":"DANMU_MSG","info":[[0,1,25,16777215,1674826549764,-1624155753,0,"f6e2e92a",0,0,0,"",0,"{}","{}",{"mode":0,"show_player_type":0,"extra":"{\"send_from_me\":false,\"mode\":0,\"color\":16777215,\"dm_type\":0,\"font_size\":25,\"player_mode\":1,\"show_player_type\":0,\"content\":\"我超2000舰\",\"user_hash\":\"4142065962\",\"emoticon_unique\":\"\",\"bulge_display\":0,\"recommend_score\":1,\"main_state_dm_color\":\"\",\"objective_state_dm_color\":\"\",\"direction\":0,\"pk_direction\":0,\"quartet_direction\":0,\"anniversary_crowd\":0,\"yeah_space_type\":\"\",\"yeah_space_url\":\"\",\"jump_to_url\":\"\",\"space_type\":\"\",\"space_url\":\"\",\"animation\":{},\"emots\":null}"},{"activity_identity":"","activity_source":0,"not_show":0}],"我超2000舰",[670098534,"王言鼎",0,0,0,10000,1,""],[],[0,0,9868950,">50000",0],["",""],0,0,null,{"ts":1674826549,"ct":"67C2DA8"},0,0,null,null,0,7]},{"cmd":"DANMU_MSG","info":[[0,1,25,16777215,1674826549788,1366110721,0,"fa4a7033",0,0,0,"",0,"{}","{}",{"mode":0,"show_player_type":0,"extra":"{\"send_from_me\":false,\"mode\":0,\"color\":16777215,\"dm_type\":0,\"font_size\":25,\"player_mode\":1,\"show_player_type\":0,\"content\":\"？？\",\"user_hash\":\"4199182387\",\"emoticon_unique\":\"\",\"bulge_display\":0,\"recommend_score\":4,\"main_state_dm_color\":\"\",\"objective_state_dm_color\":\"\",\"direction\":0,\"pk_direction\":0,\"quartet_direction\":0,\"anniversary_crowd\":0,\"yeah_space_type\":\"\",\"yeah_space_url\":\"\",\"jump_to_url\":\"\",\"space_type\":\"\",\"space_url\":\"\",\"animation\":{},\"emots\":null}"},{"activity_identity":"","activity_source":0,"not_show":0}],"？？",[2382667,"Impory莲葬",0,0,0,10000,1,""],[13,"小孩梓","阿梓从小就很可爱",80397,12478086,"",0,12632256,12632256,12632256,0,0,7706705],[20,0,6406234,">50000",0],["",""],0,0,null,{"ts":1674826549,"ct":"99CA9083"},0,0,null,null,0,42]},{"cmd":"DANMU_MSG","info":[[0,1,25,5566168,1674826549779,-1052173855,0,"60ec0b71",0,0,0,"",0,"{}","{}",{"mode":0,"show_player_type":0,"extra":"{\"send_from_me\":false,\"mode\":0,\"color\":5566168,\"dm_type\":0,\"font_size\":25,\"player_mode\":1,\"show_player_type\":0,\"content\":\"来个荔枝房管\",\"user_hash\":\"1626082161\",\"emoticon_unique\":\"\",\"bulge_display\":0,\"recommend_score\":5,\"main_state_dm_color\":\"\",\"objective_state_dm_color\":\"\",\"direction\":0,\"pk_direction\":0,\"quartet_direction\":0,\"anniversary_crowd\":0,\"yeah_space_type\":\"\",\"yeah_space_url\":\"\",\"jump_to_url\":\"\",\"space_type\":\"\",\"space_url\":\"\",\"animation\":{},\"emots\":null}"},{"activity_identity":"","activity_source":0,"not_show":0}],"来个荔枝房管",[620204816,"Utopiayy",0,0,0,10000,1,""],[7,"正鲸人","鲸鱼娘西丝特official",26545331,6126494,"",0,6126494,6126494,6126494,0,1,1398337493],[0,0,9868950,">50000",0],["",""],0,0,null,{"ts":1674826549,"ct":"4EC2CE66"},0,0,null,null,0,35]}]],"packetLen":4126,"headerLen":16,"ver":3,"op":5,"seq":0}