{"body":[[{"cmd":"DANMU_MSG","info":[[0,1,25,14893055,1676376738965,-21778779,0,"fac2b8ad",0,0,5,"#1453BAFF,#4C2263A2,#3353BAFF",0,"{}","{}",{"mode":0,"show_player_type":0,"extra":"{\"send_from_me\":false,\"mode\":0,\"color\":14893055,\"dm_type\":0,\"font_size\":25,\"player_mode\":1,\"show_player_type\":0,\"content\":\"呃呃\",\"user_hash\":\"4207065261\",\"emoticon_unique\":\"\",\"bulge_display\":0,\"recommend_score\":8,\"main_state_dm_color\":\"\",\"objective_state_dm_color\":\"\",\"direction\":0,\"pk_direction\":0,\"quartet_direction\":0,\"anniversary_crowd\":0,\"yeah_space_type\":\"\",\"yeah_space_url\":\"\",\"jump_to_url\":\"\",\"space_type\":\"\",\"space_url\":\"\",\"animation\":{},\"emots\":null}"},{"activity_identity":"","activity_source":0,"not_show":0}],"呃呃",[44667813,"阿比小太阳",0,0,0,10000,1,"#00D1F1"],[25,"瞳星结","星瞳_Official",22886883,398668,"",0,6809855,398668,6850801,3,1,401315430],[15,0,6406234,">50000",0],["",""],0,3,null,{"ts":1676376738,"ct":"F1CF78C5"},0,0,null,null,0,105]},{"cmd":"WATCHED_CHANGE","data":{"num":20864,"text_small":"2.0万","text_large":"2.0万人看过"}},{"cmd":"SEND_GIFT","data":{"action":"投喂","batch_combo_id":"batch:gift:combo_id:6082288:401315430:32564:1676376738.1187","batch_combo_send":{"action":"投喂","batch_combo_id":"batch:gift:combo_id:6082288:401315430:32564:1676376738.1187","batch_combo_num":4,"blind_gift":null,"gift_id":32564,"gift_name":"爱心戒指","gift_num":1,"send_master":null,"uid":6082288,"uname":"星瞳的心上人"},"beatId":"","biz_source":"live","blind_gift":null,"broadcast_id":0,"coin_type":"gold","combo_resources_id":1,"combo_send":null,"combo_stay_time":3,"combo_total_coin":4000,"crit_prob":0,"demarcation":2,"discount_price":1000,"dmscore":72,"draw":0,"effect":0,"effect_block":0,"face":"https://i1.hdslb.com/bfs/face/8d864b7a4be0e15887e44401b9358e7570453983.jpg","face_effect_id":0,"face_effect_type":0,"float_sc_resource_id":0,"giftId":32564,"giftName":"爱心戒指","giftType":0,"gold":0,"guard_level":0,"is_first":false,"is_join_receiver":false,"is_naming":false,"is_special_batch":0,"magnification":1,"medal_info":{"anchor_roomid":0,"anchor_uname":"","guard_level":0,"icon_id":0,"is_lighted":1,"medal_color":12478086,"medal_color_border":12478086,"medal_color_end":12478086,"medal_color_start":12478086,"medal_level":16,"medal_name":"瞳星结","special":"","target_id":401315430},"name_color":"","num":1,"original_gift_name":"","price":1000,"rcost":51804102,"receive_user_info":{"uid":401315430,"uname":"星瞳_Official"},"remain":0,"rnd":"1676376738121800007","send_master":null,"silver":0,"super":0,"super_batch_gift_num":4,"super_gift_num":4,"svga_block":0,"switch":true,"tag_image":"","tid":"1676376738121800007","timestamp":1676376738,"top_list":null,"total_coin":1000,"uid":6082288,"uname":"星瞳的心上人"}},{"cmd":"SEND_GIFT","data":{"action":"投喂","batch_combo_id":"batch:gift:combo_id:52496600:401315430:30971:1676376738.9940","batch_combo_send":{"action":"投喂","batch_combo_id":"batch:gift:combo_id:52496600:401315430:30971:1676376738.9940","batch_combo_num":1,"blind_gift":null,"gift_id":30971,"gift_name":"这个好诶","gift_num":1,"send_master":null,"uid":52496600,"uname":"摸魚的猫"},"beatId":"","biz_source":"Live","blind_gift":null,"broadcast_id":0,"coin_type":"gold","combo_resources_id":1,"combo_send":{"action":"投喂","combo_id":"gift:combo_id:52496600:401315430:30971:1676376738.9930","combo_num":1,"gift_id":30971,"gift_name":"这个好诶","gift_num":1,"send_master":null,"uid":52496600,"uname":"摸魚的猫"},"combo_stay_time":3,"combo_total_coin":1000,"crit_prob":0,"demarcation":2,"discount_price":1000,"dmscore":64,"draw":0,"effect":0,"effect_block":0,"face":"https://i2.hdslb.com/bfs/face/903338c72d6cf7c2df0824787166907b72c485fd.jpg","face_effect_id":0,"face_effect_type":0,"float_sc_resource_id":0,"giftId":30971,"giftName":"这个好诶","giftType":0,"gold":0,"guard_level":0,"is_first":true,"is_join_receiver":false,"is_naming":false,"is_special_batch":0,"magnification":1,"medal_info":{"anchor_roomid":0,"anchor_uname":"","guard_level":0,"icon_id":0,"is_lighted":1,"medal_color":13081892,"medal_color_border":13081892,"medal_color_end":13081892,"medal_color_start":13081892,"medal_level":17,"medal_name":"老菊","special":"","target_id":423895},"name_color":"","num":1,"original_gift_name":"","price":1000,"rcost":51804102,"receive_user_info":{"uid":401315430,"uname":"星瞳_Official"},"remain":0,"rnd":"1676376738121000004","send_master":null,"silver":0,"super":0,"super_batch_gift_num":1,"super_gift_num":1,"svga_block":0,"switch":true,"tag_image":"","tid":"1676376738121000004","timestamp":1676376738,"top_list":null,"total_coin":1000,"uid":52496600,"uname":"摸魚的猫"}},{"cmd":"DANMU_MSG","info":[[0,1,25,5566168,1676376739012,675364232,0,"88ff9215",0,0,0,"",0,"{}","{}",{"mode":0,"show_player_type":0,"extra":"{\"send_from_me\":false,\"mode\":0,\"color\":5566168,\"dm_type\":0,\"font_size\":25,\"player_mode\":1,\"show_player_type\":0,\"content\":\"我是文盲，不会算\",\"user_hash\":\"2298450453\",\"emoticon_unique\":\"\",\"bulge_display\":0,\"recommend_score\":2,\"main_state_dm_color\":\"\",\"objective_state_dm_color\":\"\",\"direction\":0,\"pk_direction\":0,\"quartet_direction\":0,\"anniversary_crowd\":0,\"yeah_space_type\":\"\",\"yeah_space_url\":\"\",\"jump_to_url\":\"\",\"space_type\":\"\",\"space_url\":\"\",\"animation\":{},\"emots\":null}"},{"activity_identity":"","activity_source":0,"not_show":0}],"我是文盲，不会算",[37319032,"Bili_37319032",0,0,0,10000,1,""],[10,"瞳星结","星瞳_Official",22886883,9272486,"",0,9272486,9272486,9272486,0,1,401315430],[2,0,9868950,">50000",0],["",""],0,0,null,{"ts":1676376739,"ct":"6DB436AB"},0,0,null,null,0,49]},{"cmd":"INTERACT_WORD","data":{"contribution":{"grade":0},"core_user_type":0,"dmscore":16,"fans_medal":{"anchor_roomid":21452505,"guard_level":0,"icon_id":0,"is_lighted":0,"medal_color":12478086,"medal_color_border":12632256,"medal_color_end":12632256,"medal_color_start":12632256,"medal_level":15,"medal_name":"脆鲨","score":63851,"special":"","target_id":434334701},"identities":[1],"is_spread":0,"msg_type":1,"privilege_type":0,"roomid":22886883,"score":1676376738148,"spread_desc":"","spread_info":"","tail_icon":0,"timestamp":1676376738,"trigger_time":1676376737125211100,"uid":6970763,"uname":"Ltimpice","uname_color":""}},{"cmd":"INTERACT_WORD","data":{"contribution":{"grade":0},"core_user_type":0,"dmscore":16,"fans_medal":{"anchor_roomid":22603245,"guard_level":0,"icon_id":0,"is_lighted":1,"medal_color":13081892,"medal_color_border":13081892,"medal_color_end":13081892,"medal_color_start":13081892,"medal_level":17,"medal_name":"雏草姬","score":158715,"special":"","target_id":1265680561},"identities":[3,1],"is_spread":0,"msg_type":1,"privilege_type":0,"roomid":22886883,"score":1676545453606,"spread_desc":"","spread_info":"","tail_icon":0,"timestamp":1676376738,"trigger_time":1676376737541833000,"uid":25857868,"uname":"放弃不确定性","uname_color":""}},{"cmd":"SEND_GIFT","data":{"action":"投喂","batch_combo_id":"batch:gift:combo_id:6082288:401315430:32564:1676376738.1187","batch_combo_send":{"action":"投喂","batch_combo_id":"batch:gift:combo_id:6082288:401315430:32564:1676376738.1187","batch_combo_num":5,"blind_gift":null,"gift_id":32564,"gift_name":"爱心戒指","gift_num":1,"send_master":null,"uid":6082288,"uname":"星瞳的心上人"},"beatId":"","biz_source":"live","blind_gift":null,"broadcast_id":0,"coin_type":"gold","combo_resources_id":1,"combo_send":null,"combo_stay_time":3,"combo_total_coin":5000,"crit_prob":0,"demarcation":2,"discount_price":1000,"dmscore":72,"draw":0,"effect":0,"effect_block":0,"face":"https://i1.hdslb.com/bfs/face/8d864b7a4be0e15887e44401b9358e7570453983.jpg","face_effect_id":0,"face_effect_type":0,"float_sc_resource_id":0,"giftId":32564,"giftName":"爱心戒指","giftType":0,"gold":0,"guard_level":0,"is_first":false,"is_join_receiver":false,"is_naming":false,"is_special_batch":0,"magnification":1,"medal_info":{"anchor_roomid":0,"anchor_uname":"","guard_level":0,"icon_id":0,"is_lighted":1,"medal_color":12478086,"medal_color_border":12478086,"medal_color_end":12478086,"medal_color_start":12478086,"medal_level":16,"medal_name":"瞳星结","special":"","target_id":401315430},"name_color":"","num":1,"original_gift_name":"","price":1000,"rcost":51804102,"receive_user_info":{"uid":401315430,"uname":"星瞳_Official"},"remain":0,"rnd":"1676376739121800001","send_master":null,"silver":0,"super":0,"super_batch_gift_num":5,"super_gift_num":5,"svga_block":0,"switch":true,"tag_image":"","tid":"1676376739121800001","timestamp":1676376739,"top_list":null,"total_coin":1000,"uid":6082288,"uname":"星瞳的心上人"}},{"cmd":"DANMU_MSG","info":[[0,1,25,5816798,1676376739203,691503400,0,"2aa2867f",0,0,0,"",0,"{}","{}",{"mode":0,"show_player_type":0,"extra":"{\"send_from_me\":false,\"mode\":0,\"color\":5816798,\"dm_type\":0,\"font_size\":25,\"player_mode\":1,\"show_player_type\":0,\"content\":\"头晕了\",\"user_hash\":\"715294335\",\"emoticon_unique\":\"\",\"bulge_display\":0,\"recommend_score\":7,\"main_state_dm_color\":\"\",\"objective_state_dm_color\":\"\",\"direction\":0,\"pk_direction\":0,\"quartet_direction\":0,\"anniversary_crowd\":0,\"yeah_space_type\":\"\",\"yeah_space_url\":\"\",\"jump_to_url\":\"\",\"space_type\":\"\",\"space_url\":\"\",\"animation\":{},\"emots\":null}"},{"activity_identity":"","activity_source":0,"not_show":0}],"头晕了",[413483568,"还是瞳瞳对我好",0,0,0,10000,1,""],[21,"瞳星结","星瞳_Official",22886883,1725515,"",0,1725515,1725515,5414290,0,1,401315430],[2,0,9868950,">50000",0],["",""],0,0,null,{"ts":1676376739,"ct":"4A61BBA"},0,0,null,null,0,63]},{"cmd":"DANMU_MSG","info":[[0,4,25,14893055,1676376739252,1676375553,0,"bcae247b",0,0,5,"#1453BAFF,#4C2263A2,#3353BAFF",0,"{}","{}",{"mode":0,"show_player_type":0,"extra":"{\"send_from_me\":false,\"mode\":0,\"color\":14893055,\"dm_type\":0,\"font_size\":25,\"player_mode\":1,\"show_player_type\":0,\"content\":\"清华大学请求出战\",\"user_hash\":\"3165529211\",\"emoticon_unique\":\"\",\"bulge_display\":0,\"recommend_score\":5,\"main_state_dm_color\":\"\",\"objective_state_dm_color\":\"\",\"direction\":0,\"pk_direction\":0,\"quartet_direction\":0,\"anniversary_crowd\":0,\"yeah_space_type\":\"\",\"yeah_space_url\":\"\",\"jump_to_url\":\"\",\"space_type\":\"\",\"space_url\":\"\",\"animation\":{},\"emots\":null}"},{"activity_identity":"","activity_source":0,"not_show":0}],"清华大学请求出战",[630972445,"あい灰灰狗L",0,0,0,10000,1,"#00D1F1"],[23,"瞳星结","星瞳_Official",22886883,1725515,"",0,6809855,1725515,5414290,3,1,401315430],[7,0,9868950,">50000",0],["",""],0,3,null,{"ts":1676376739,"ct":"803BFA05"},0,0,null,null,0,105]},{"cmd":"DANMU_MSG","info":[[0,1,25,4546550,1676376739240,-1237737565,0,"2c285aa2",0,0,0,"",0,"{}","{}",{"mode":0,"show_player_type":0,"extra":"{\"send_from_me\":false,\"mode\":0,\"color\":4546550,\"dm_type\":0,\"font_size\":25,\"player_mode\":1,\"show_player_type\":0,\"content\":\"呃呃\",\"user_hash\":\"740842146\",\"emoticon_unique\":\"\",\"bulge_display\":0,\"recommend_score\":9,\"main_state_dm_color\":\"\",\"objective_state_dm_color\":\"\",\"direction\":0,\"pk_direction\":0,\"quartet_direction\":0,\"anniversary_crowd\":0,\"yeah_space_type\":\"\",\"yeah_space_url\":\"\",\"jump_to_url\":\"\",\"space_type\":\"\",\"space_url\":\"\",\"animation\":{},\"emots\":null}"},{"activity_identity":"","activity_source":0,"not_show":0}],"呃呃",[692159388,"111111斤斤计较",0,0,0,10000,1,""],[23,"瞳星结","星瞳_Official",22886883,1725515,"",0,1725515,1725515,5414290,0,1,401315430],[13,0,6406234,">50000",0],["",""],0,0,null,{"ts":1676376739,"ct":"B21F1F8D"},0,0,null,null,0,63]},{"cmd":"DANMU_MSG","info":[[0,4,25,14893055,1676376739288,-44426449,0,"f0a9f60d",0,0,5,"#1453BAFF,#4C2263A2,#3353BAFF",0,"{}","{}",{"mode":0,"show_player_type":0,"extra":"{\"send_from_me\":false,\"mode\":0,\"color\":14893055,\"dm_type\":0,\"font_size\":25,\"player_mode\":4,\"show_player_type\":0,\"content\":\"土土土\",\"user_hash\":\"4037670413\",\"emoticon_unique\":\"\",\"bulge_display\":0,\"recommend_score\":7,\"main_state_dm_color\":\"\",\"objective_state_dm_color\":\"\",\"direction\":0,\"pk_direction\":0,\"quartet_direction\":0,\"anniversary_crowd\":0,\"yeah_space_type\":\"\",\"yeah_space_url\":\"\",\"jump_to_url\":\"\",\"space_type\":\"\",\"space_url\":\"\",\"animation\":{},\"emots\":null}"},{"activity_identity":"","activity_source":0,"not_show":0}],"土土土",[71373362,"大智慧a",0,0,0,10000,1,"#00D1F1"],[25,"瞳星结","星瞳_Official",22886883,398668,"",0,6809855,398668,6850801,3,1,401315430],[13,0,6406234,">50000",0],["",""],0,3,null,{"ts":1676376739,"ct":"EBF6C839"},0,0,null,null,0,105]},{"cmd":"DANMU_MSG","info":[[0,4,25,14893055,1676376739267,1676375447,0,"8eb6db3b",0,0,5,"#1453BAFF,#4C2263A2,#3353BAFF",0,"{}","{}",{"mode":0,"show_player_type":0,"extra":"{\"send_from_me\":false,\"mode\":0,\"color\":14893055,\"dm_type\":0,\"font_size\":25,\"player_mode\":4,\"show_player_type\":0,\"content\":\"好好好\",\"user_hash\":\"2394348347\",\"emoticon_unique\":\"\",\"bulge_display\":0,\"recommend_score\":1,\"main_state_dm_color\":\"\",\"objective_state_dm_color\":\"\",\"direction\":0,\"pk_direction\":0,\"quartet_direction\":0,\"anniversary_crowd\":0,\"yeah_space_type\":\"\",\"yeah_space_url\":\"\",\"jump_to_url\":\"\",\"space_type\":\"\",\"space_url\":\"\",\"animation\":{},\"emots\":null}"},{"activity_identity":"","activity_source":0,"not_show":0}],"好好好",[381586853,"7谭",0,0,0,10000,1,"#00D1F1"],[],[13,0,6406234,">50000",0],["",""],0,3,null,{"ts":1676376739,"ct":"25943808"},0,0,null,null,0,105]},{"cmd":"DANMU_MSG","info":[[0,4,25,14893055,1676376739437,1676375944,0,"c650c204",0,0,5,"#1453BAFF,#4C2263A2,#3353BAFF",0,"{}","{}",{"mode":0,"show_player_type":0,"extra":"{\"send_from_me\":false,\"mode\":0,\"color\":14893055,\"dm_type\":0,\"font_size\":25,\"player_mode\":1,\"show_player_type\":0,\"content\":\"我晕了\",\"user_hash\":\"3327181316\",\"emoticon_unique\":\"\",\"bulge_display\":0,\"recommend_score\":3,\"main_state_dm_color\":\"\",\"objective_state_dm_color\":\"\",\"direction\":0,\"pk_direction\":0,\"quartet_direction\":0,\"anniversary_crowd\":0,\"yeah_space_type\":\"\",\"yeah_space_url\":\"\",\"jump_to_url\":\"\",\"space_type\":\"\",\"space_url\":\"\",\"animation\":{},\"emots\":null}"},{"activity_identity":"","activity_source":0,"not_show":0}],"我晕了",[162579305,"衣襟褧衣",0,0,0,10000,1,"#00D1F1"],[25,"瞳星结","星瞳_Official",22886883,398668,"",0,6809855,398668,6850801,3,1,401315430],[15,0,6406234,">50000",0],["",""],0,3,null,{"ts":1676376739,"ct":"DDA27A83"},0,0,null,null,0,105]},{"cmd":"COMBO_SEND","data":{"action":"投喂","batch_combo_id":"batch:gift:combo_id:178396690:401315430:31164:1676376734.3966","batch_combo_num":6,"combo_id":"gift:combo_id:178396690:401315430:31164:1676376734.3932","combo_num":6,"combo_total_coin":6000,"dmscore":56,"gift_id":31164,"gift_name":"粉丝团灯牌","gift_num":1,"is_join_receiver":false,"is_naming":false,"is_show":1,"medal_info":{"anchor_roomid":0,"anchor_uname":"","guard_level":0,"icon_id":0,"is_lighted":1,"medal_color":9272486,"medal_color_border":9272486,"medal_color_end":9272486,"medal_color_start":9272486,"medal_level":12,"medal_name":"瞳星结","special":"","target_id":401315430},"name_color":"","r_uname":"星瞳_Official","receive_user_info":{"uid":401315430,"uname":"星瞳_Official"},"ruid":401315430,"send_master":null,"total_num":6,"uid":178396690,"uname":"安可小只因"}},{"cmd":"DANMU_MSG","info":[[0,1,25,5566168,1676376739515,1676375957,0,"68c875ce",0,0,0,"",0,"{}","{}",{"mode":0,"show_player_type":0,"extra":"{\"send_from_me\":false,\"mode\":0,\"color\":5566168,\"dm_type\":0,\"font_size\":25,\"player_mode\":1,\"show_player_type\":0,\"content\":\"投降\",\"user_hash\":\"1757967822\",\"emoticon_unique\":\"\",\"bulge_display\":0,\"recommend_score\":9,\"main_state_dm_color\":\"\",\"objective_state_dm_color\":\"\",\"direction\":0,\"pk_direction\":0,\"quartet_direction\":0,\"anniversary_crowd\":0,\"yeah_space_type\":\"\",\"yeah_space_url\":\"\",\"jump_to_url\":\"\",\"space_type\":\"\",\"space_url\":\"\",\"animation\":{},\"emots\":null}"},{"activity_identity":"","activity_source":0,"not_show":0}],"投降",[11457551,"阿夸你在做什么啊阿夸",0,0,0,10000,1,""],[12,"瞳星结","星瞳_Official",22886883,9272486,"",0,9272486,9272486,9272486,0,1,401315430],[15,0,6406234,">50000",0],["",""],0,0,null,{"ts":1676376739,"ct":"B684305D"},0,0,null,null,0,49]},{"cmd":"DANMU_MSG","info":[[0,1,25,5566168,1676376739681,1676376437,0,"664ee193",0,0,0,"",0,"{}","{}",{"mode":0,"show_player_type":0,"extra":"{\"send_from_me\":false,\"mode\":0,\"color\":5566168,\"dm_type\":0,\"font_size\":25,\"player_mode\":1,\"show_player_type\":0,\"content\":\"我中专我好几\",\"user_hash\":\"1716445587\",\"emoticon_unique\":\"\",\"bulge_display\":0,\"recommend_score\":8,\"main_state_dm_color\":\"\",\"objective_state_dm_color\":\"\",\"direction\":0,\"pk_direction\":0,\"quartet_direction\":0,\"anniversary_crowd\":0,\"yeah_space_type\":\"\",\"yeah_space_url\":\"\",\"jump_to_url\":\"\",\"space_type\":\"\",\"space_url\":\"\",\"animation\":{},\"emots\":null}"},{"activity_identity":"","activity_source":0,"not_show":0}],"我中专我好几",[31268646,"2022511_",0,0,0,10000,1,""],[10,"瞳星结","星瞳_Official",22886883,9272486,"",0,12632256,12632256,12632256,0,0,401315430],[12,0,6406234,">50000",0],["",""],0,0,null,{"ts":1676376739,"ct":"B7CC373D"},0,0,null,null,0,49]},{"cmd":"DANMU_MSG","info":[[0,4,25,14893055,1676376739701,1676375377,0,"beaf2393",0,0,5,"#1453BAFF,#4C2263A2,#3353BAFF",0,"{}","{}",{"mode":0,"show_player_type":0,"extra":"{\"send_from_me\":false,\"mode\":0,\"color\":14893055,\"dm_type\":0,\"font_size\":25,\"player_mode\":1,\"show_player_type\":0,\"content\":\"好好好\",\"user_hash\":\"3199148947\",\"emoticon_unique\":\"\",\"bulge_display\":0,\"recommend_score\":9,\"main_state_dm_color\":\"\",\"objective_state_dm_color\":\"\",\"direction\":0,\"pk_direction\":0,\"quartet_direction\":0,\"anniversary_crowd\":0,\"yeah_space_type\":\"\",\"yeah_space_url\":\"\",\"jump_to_url\":\"\",\"space_type\":\"\",\"space_url\":\"\",\"animation\":{},\"emots\":null}"},{"activity_identity":"","activity_source":0,"not_show":0}],"好好好",[2054580340,"hxy2568",0,0,0,10000,1,"#00D1F1"],[23,"瞳星结","星瞳_Official",22886883,1725515,"",0,6809855,1725515,5414290,3,1,401315430],[5,0,9868950,">50000",0],["",""],0,3,null,{"ts":1676376739,"ct":"E5817945"},0,0,null,null,0,105]},{"cmd":"DANMU_MSG","info":[[0,1,25,5816798,1676376739742,1676405538,0,"029787d7",0,0,0,"",0,"{}","{}",{"mode":0,"show_player_type":0,"extra":"{\"send_from_me\":false,\"mode\":0,\"color\":5816798,\"dm_type\":0,\"font_size\":25,\"player_mode\":1,\"show_player_type\":0,\"content\":\"已经睡着了\",\"user_hash\":\"43485143\",\"emoticon_unique\":\"\",\"bulge_display\":0,\"recommend_score\":3,\"main_state_dm_color\":\"\",\"objective_state_dm_color\":\"\",\"direction\":0,\"pk_direction\":0,\"quartet_direction\":0,\"anniversary_crowd\":0,\"yeah_space_type\":\"\",\"yeah_space_url\":\"\",\"jump_to_url\":\"\",\"space_type\":\"\",\"space_url\":\"\",\"animation\":{},\"emots\":null}"},{"activity_identity":"","activity_source":0,"not_show":0}],"已经睡着了",[351158654,"绥辩遂变随便",0,0,0,10000,1,""],[15,"瞳星结","星瞳_Official",22886883,12478086,"",0,12478086,12478086,12478086,0,1,401315430],[3,0,9868950,">50000",0],["",""],0,0,null,{"ts":1676376739,"ct":"7070A611"},0,0,null,null,0,63]},{"cmd":"DANMU_MSG","info":[[0,1,25,16777215,1676376739776,493473624,0,"24e1b7df",0,0,0,"",0,"{}","{}",{"mode":0,"show_player_type":0,"extra":"{\"send_from_me\":false,\"mode\":0,\"color\":16777215,\"dm_type\":0,\"font_size\":25,\"player_mode\":1,\"show_player_type\":0,\"content\":\"好好好\",\"user_hash\":\"618772447\",\"emoticon_unique\":\"\",\"bulge_display\":0,\"recommend_score\":3,\"main_state_dm_color\":\"\",\"objective_state_dm_color\":\"\",\"direction\":0,\"pk_direction\":0,\"quartet_direction\":0,\"anniversary_crowd\":0,\"yeah_space_type\":\"\",\"yeah_space_url\":\"\",\"jump_to_url\":\"\",\"space_type\":\"\",\"space_url\":\"\",\"animation\":{},\"emots\":null}"},{"activity_identity":"","activity_source":0,"not_show":0}],"好好好",[213987241,"谜之觋",0,0,0,10000,1,""],[4,"锦依卫","洛天依",1546736,6067854,"",0,12632256,12632256,12632256,0,0,36081646],[10,0,9868950,">50000",0],["",""],0,0,null,{"ts":1676376739,"ct":"12FD2892"},0,0,null,null,0,14]},{"cmd":"DANMU_MSG","info":[[0,1,25,5566168,1676376739849,1676376320,0,"fa4c3aa2",0,0,0,"",0,"{}","{}",{"mode":0,"show_player_type":0,"extra":"{\"send_from_me\":false,\"mode\":0,\"color\":5566168,\"dm_type\":0,\"font_size\":25,\"player_mode\":1,\"show_player_type\":0,\"content\":\"一个圆圈\",\"user_hash\":\"4199299746\",\"emoticon_unique\":\"\",\"bulge_display\":0,\"recommend_score\":4,\"main_state_dm_color\":\"\",\"objective_state_dm_color\":\"\",\"direction\":0,\"pk_direction\":0,\"quartet_direction\":0,\"anniversary_crowd\":0,\"yeah_space_type\":\"\",\"yeah_space_url\":\"\",\"jump_to_url\":\"\",\"space_type\":\"\",\"space_url\":\"\",\"animation\":{},\"emots\":null}"},{"activity_identity":"","activity_source":0,"not_show":0}],"一个圆圈",[24576274,"建议改名不要币",0,0,0,10000,1,""],[24,"美人虞","虞莫MOMO",25512485,1725515,"",0,6809855,1725515,5414290,3,1,1811071010],[14,0,6406234,">50000",0],["",""],0,0,null,{"ts":1676376739,"ct":"8500AC85"},0,0,null,null,0,70]},{"cmd":"DANMU_MSG","info":[[0,1,25,5816798,1676376739925,1897226895,0,"1bea23cf",0,0,0,"",0,"{}","{}",{"mode":0,"show_player_type":0,"extra":"{\"send_from_me\":false,\"mode\":0,\"color\":5816798,\"dm_type\":0,\"font_size\":25,\"player_mode\":1,\"show_player_type\":0,\"content\":\"呃呃\",\"user_hash\":\"468329423\",\"emoticon_unique\":\"\",\"bulge_display\":0,\"recommend_score\":9,\"main_state_dm_color\":\"\",\"objective_state_dm_color\":\"\",\"direction\":0,\"pk_direction\":0,\"quartet_direction\":0,\"anniversary_crowd\":0,\"yeah_space_type\":\"\",\"yeah_space_url\":\"\",\"jump_to_url\":\"\",\"space_type\":\"\",\"space_url\":\"\",\"animation\":{},\"emots\":null}"},{"activity_identity":"","activity_source":0,"not_show":0}],"呃呃",[14334799,"Jaceimba321",0,0,0,10000,1,""],[10,"熹米露","露米Lumi_Official",25977291,9272486,"",0,9272486,9272486,9272486,0,1,2000609327],[7,0,9868950,">50000",0],["",""],0,0,null,{"ts":1676376739,"ct":"1B7F6597"},0,0,null,null,0,42]}]],"packetLen":3032,"headerLen":16,"ver":3,"op":5,"seq":0}