{"body":[[{"cmd":"ENTRY_EFFECT","data":{"id":4,"uid":100221791,"target_id":1265680561,"mock_effect":0,"face":"https://i2.hdslb.com/bfs/face/07ff8815a89118091c964a6326d48a0767382448.jpg","privilege_type":3,"copy_writing":"欢迎舰长 <%cfm单推人%> 进入直播间","copy_color":"#ffffff","highlight_color":"#E6FF00","priority":1,"basemap_url":"https://i0.hdslb.com/bfs/live/mlive/11a6e8eb061c3e715d0a6a2ac0ddea2faa15c15e.png","show_avatar":1,"effective_time":2,"web_basemap_url":"https://i0.hdslb.com/bfs/live/mlive/11a6e8eb061c3e715d0a6a2ac0ddea2faa15c15e.png","web_effective_time":2,"web_effect_close":0,"web_close_time":0,"business":1,"copy_writing_v2":"欢迎舰长 <%cfm单推人%> 进入直播间","icon_list":[],"max_delay_time":7,"trigger_time":1672488080141276400,"identities":6,"effect_silent_time":0,"effective_time_new":0,"web_dynamic_url_webp":"","web_dynamic_url_apng":"","mobile_dynamic_url_webp":""}},{"cmd":"DANMU_MSG","info":[[0,1,25,16777215,1672488081260,384365975,0,"6e6c41dc",0,0,0,"",0,"{}","{}",{"mode":0,"show_player_type":0,"extra":"{\"send_from_me\":false,\"mode\":0,\"color\":16777215,\"dm_type\":0,\"font_size\":25,\"player_mode\":1,\"show_player_type\":0,\"content\":\"么么么么么么么么\",\"user_hash\":\"1852588508\",\"emoticon_unique\":\"\",\"bulge_display\":0,\"recommend_score\":7,\"main_state_dm_color\":\"\",\"objective_state_dm_color\":\"\",\"direction\":0,\"pk_direction\":0,\"quartet_direction\":0,\"anniversary_crowd\":0,\"yeah_space_type\":\"\",\"yeah_space_url\":\"\",\"jump_to_url\":\"\",\"space_type\":\"\",\"space_url\":\"\",\"animation\":{},\"emots\":null}"},{"activity_identity":"","activity_source":0,"not_show":0}],"么么么么么么么么",[426875910,"寄寄寄寄1",0,0,0,10000,1,""],[],[0,0,9868950,">50000",0],["",""],0,0,null,{"ts":1672488081,"ct":"36991F6B"},0,0,null,null,0,7]},{"cmd":"DANMU_MSG","info":[[0,1,25,16777215,1672488081323,992493768,0,"664ee5cb",0,0,0,"",1,{"bulge_display":1,"emoticon_unique":"room_22603245_2759","height":162,"in_player_area":1,"is_dynamic":0,"url":"http://i0.hdslb.com/bfs/live/8a387d478d57b3e2c5ba6a8a29046f417ff4980f.png","width":162},"{}",{"mode":0,"show_player_type":0,"extra":"{\"send_from_me\":false,\"mode\":0,\"color\":16777215,\"dm_type\":1,\"font_size\":25,\"player_mode\":1,\"show_player_type\":0,\"content\":\"呜呜呜\",\"user_hash\":\"1716446667\",\"emoticon_unique\":\"room_22603245_2759\",\"bulge_display\":1,\"recommend_score\":4,\"main_state_dm_color\":\"\",\"objective_state_dm_color\":\"\",\"direction\":0,\"pk_direction\":0,\"quartet_direction\":0,\"anniversary_crowd\":0,\"yeah_space_type\":\"\",\"yeah_space_url\":\"\",\"jump_to_url\":\"\",\"space_type\":\"\",\"space_url\":\"\",\"animation\":{},\"emots\":null}"},{"activity_identity":"","activity_source":0,"not_show":0}],"呜呜呜",[176904398,"-兰佩路基-",0,0,0,10000,1,""],[22,"光星","白夜光来",26415245,1725515,"",0,6809855,1725515,5414290,3,1,3493081015913390],[12,0,6406234,">50000",0],["",""],0,0,null,{"ts":1672488081,"ct":"11478DCB"},0,0,null,null,0,70]},{"cmd":"SEND_GIFT","data":{"action":"投喂","batch_combo_id":"","batch_combo_send":null,"beatId":"","biz_source":"live","blind_gift":null,"broadcast_id":0,"coin_type":"silver","combo_resources_id":1,"combo_send":null,"combo_stay_time":3,"combo_total_coin":0,"crit_prob":0,"demarcation":1,"discount_price":0,"dmscore":20,"draw":0,"effect":0,"effect_block":1,"face":"https://i1.hdslb.com/bfs/baselabs/74238e16acf88aa810e2a2ef31416c8d34fbc13e.png","face_effect_id":0,"face_effect_type":0,"float_sc_resource_id":0,"giftId":1,"giftName":"辣条","giftType":5,"gold":0,"guard_level":0,"is_first":true,"is_join_receiver":false,"is_naming":false,"is_special_batch":0,"magnification":1,"medal_info":{"anchor_roomid":0,"anchor_uname":"","guard_level":0,"icon_id":0,"is_lighted":1,"medal_color":6126494,"medal_color_border":6126494,"medal_color_end":6126494,"medal_color_start":6126494,"medal_level":7,"medal_name":"雏草姬","special":"","target_id":1265680561},"name_color":"","num":1,"original_gift_name":"","price":100,"rcost":66758956,"receive_user_info":{"uid":1265680561,"uname":"永雏塔菲"},"remain":32,"rnd":"1672488081120600002","send_master":null,"silver":0,"super":0,"super_batch_gift_num":0,"super_gift_num":0,"svga_block":0,"switch":true,"tag_image":"","tid":"1672488081120600002","timestamp":1672488081,"top_list":null,"total_coin":100,"uid":670620736,"uname":"肖战粉丝梅麻"}},{"cmd":"DANMU_MSG","info":[[0,1,25,5816798,1672488081366,342388420,0,"ecb456a9",0,0,0,"",1,{"bulge_display":1,"emoticon_unique":"room_22603245_2843","height":162,"in_player_area":1,"is_dynamic":1,"url":"http://i0.hdslb.com/bfs/garb/087b9eb7026fc627f16d70503044096254ba636b.png","width":162},"{}",{"mode":0,"show_player_type":0,"extra":"{\"send_from_me\":false,\"mode\":0,\"color\":5816798,\"dm_type\":1,\"font_size\":25,\"player_mode\":1,\"show_player_type\":0,\"content\":\"啊啊\",\"user_hash\":\"3971241641\",\"emoticon_unique\":\"room_22603245_2843\",\"bulge_display\":1,\"recommend_score\":3,\"main_state_dm_color\":\"\",\"objective_state_dm_color\":\"\",\"direction\":0,\"pk_direction\":0,\"quartet_direction\":0,\"anniversary_crowd\":0,\"yeah_space_type\":\"\",\"yeah_space_url\":\"\",\"jump_to_url\":\"\",\"space_type\":\"\",\"space_url\":\"\",\"animation\":{},\"emots\":null}"},{"activity_identity":"","activity_source":0,"not_show":0}],"啊啊",[26099609,"丝断魂",0,0,0,10000,1,""],[16,"雏草姬","永雏塔菲",22603245,12478086,"",0,12478086,12478086,12478086,0,1,1265680561],[10,0,9868950,">50000",0],["",""],0,0,null,{"ts":1672488081,"ct":"BF92DD62"},0,0,null,null,0,63]},{"cmd":"SEND_GIFT","data":{"action":"投喂","batch_combo_id":"","batch_combo_send":null,"beatId":"","biz_source":"live","blind_gift":null,"broadcast_id":0,"coin_type":"silver","combo_resources_id":1,"combo_send":null,"combo_stay_time":3,"combo_total_coin":0,"crit_prob":0,"demarcation":1,"discount_price":0,"dmscore":20,"draw":0,"effect":0,"effect_block":1,"face":"https://i1.hdslb.com/bfs/baselabs/74238e16acf88aa810e2a2ef31416c8d34fbc13e.png","face_effect_id":0,"face_effect_type":0,"float_sc_resource_id":0,"giftId":1,"giftName":"辣条","giftType":5,"gold":0,"guard_level":0,"is_first":true,"is_join_receiver":false,"is_naming":false,"is_special_batch":0,"magnification":1,"medal_info":{"anchor_roomid":0,"anchor_uname":"","guard_level":0,"icon_id":0,"is_lighted":1,"medal_color":6126494,"medal_color_border":6126494,"medal_color_end":6126494,"medal_color_start":6126494,"medal_level":7,"medal_name":"雏草姬","special":"","target_id":1265680561},"name_color":"","num":1,"original_gift_name":"","price":100,"rcost":66758956,"receive_user_info":{"uid":1265680561,"uname":"永雏塔菲"},"remain":31,"rnd":"1672488081120600006","send_master":null,"silver":0,"super":0,"super_batch_gift_num":0,"super_gift_num":0,"svga_block":0,"switch":true,"tag_image":"","tid":"1672488081120600006","timestamp":1672488081,"top_list":null,"total_coin":100,"uid":670620736,"uname":"肖战粉丝梅麻"}},{"cmd":"DANMU_MSG","info":[[0,1,25,16777215,1672488081447,-1899509963,0,"e506229e",0,0,0,"",0,"{}","{}",{"mode":0,"show_player_type":0,"extra":"{\"send_from_me\":false,\"mode\":0,\"color\":16777215,\"dm_type\":0,\"font_size\":25,\"player_mode\":1,\"show_player_type\":0,\"content\":\"急急急\",\"user_hash\":\"3842384542\",\"emoticon_unique\":\"\",\"bulge_display\":0,\"recommend_score\":0,\"main_state_dm_color\":\"\",\"objective_state_dm_color\":\"\",\"direction\":0,\"pk_direction\":0,\"quartet_direction\":0,\"anniversary_crowd\":0,\"yeah_space_type\":\"\",\"yeah_space_url\":\"\",\"jump_to_url\":\"\",\"space_type\":\"\",\"space_url\":\"\",\"animation\":{},\"emots\":null}"},{"activity_identity":"","activity_source":0,"not_show":0}],"急急急",[260114818,"瘾硫枸",0,0,0,10000,1,""],[4,"雏草姬","永雏塔菲",22603245,6067854,"",0,6067854,6067854,6067854,0,1,1265680561],[4,0,9868950,">50000",0],["",""],0,0,null,{"ts":1672488081,"ct":"D18DCC58"},0,0,null,null,0,28]},{"cmd":"DANMU_MSG","info":[[0,4,25,14893055,1672488081525,1672488007,0,"1db74190",0,0,2,"#19897EFF,#403F388E,#33897EFF",0,"{}","{}",{"mode":0,"show_player_type":0,"extra":"{\"send_from_me\":false,\"mode\":0,\"color\":14893055,\"dm_type\":0,\"font_size\":25,\"player_mode\":4,\"show_player_type\":0,\"content\":\"喵喵喵\",\"user_hash\":\"498549136\",\"emoticon_unique\":\"\",\"bulge_display\":0,\"recommend_score\":7,\"main_state_dm_color\":\"\",\"objective_state_dm_color\":\"\",\"direction\":0,\"pk_direction\":0,\"quartet_direction\":0,\"anniversary_crowd\":0,\"yeah_space_type\":\"\",\"yeah_space_url\":\"\",\"jump_to_url\":\"\",\"space_type\":\"\",\"space_url\":\"\",\"animation\":{},\"emots\":null}"},{"activity_identity":"","activity_source":0,"not_show":0}],"喵喵喵",[11566793,"狱明",0,0,0,10000,1,"#E17AFF"],[27,"雏草姬","永雏塔菲",22603245,398668,"",0,16771156,398668,6850801,2,1,1265680561],[20,0,6406234,">50000",0],["",""],0,2,null,{"ts":1672488081,"ct":"85EF3FCA"},0,0,null,null,0,112]},{"cmd":"SEND_GIFT","data":{"action":"投喂","batch_combo_id":"","batch_combo_send":null,"beatId":"","biz_source":"live","blind_gift":null,"broadcast_id":0,"coin_type":"silver","combo_resources_id":1,"combo_send":null,"combo_stay_time":3,"combo_total_coin":0,"crit_prob":0,"demarcation":1,"discount_price":0,"dmscore":20,"draw":0,"effect":0,"effect_block":1,"face":"https://i1.hdslb.com/bfs/baselabs/74238e16acf88aa810e2a2ef31416c8d34fbc13e.png","face_effect_id":0,"face_effect_type":0,"float_sc_resource_id":0,"giftId":1,"giftName":"辣条","giftType":5,"gold":0,"guard_level":0,"is_first":true,"is_join_receiver":false,"is_naming":false,"is_special_batch":0,"magnification":1,"medal_info":{"anchor_roomid":0,"anchor_uname":"","guard_level":0,"icon_id":0,"is_lighted":1,"medal_color":6126494,"medal_color_border":6126494,"medal_color_end":6126494,"medal_color_start":6126494,"medal_level":7,"medal_name":"雏草姬","special":"","target_id":1265680561},"name_color":"","num":1,"original_gift_name":"","price":100,"rcost":66758956,"receive_user_info":{"uid":1265680561,"uname":"永雏塔菲"},"remain":30,"rnd":"1672488081120600009","send_master":null,"silver":0,"super":0,"super_batch_gift_num":0,"super_gift_num":0,"svga_block":0,"switch":true,"tag_image":"","tid":"1672488081120600009","timestamp":1672488081,"top_list":null,"total_coin":100,"uid":670620736,"uname":"肖战粉丝梅麻"}},{"cmd":"ONLINE_RANK_V2","data":{"list":[{"uid":12318726,"face":"https://i0.hdslb.com/bfs/face/7d8c460c0e9175f6dfdce8373a2a71c83c392484.jpg","score":"1382","uname":"来一杯明前奶绿喵","rank":1,"guard_level":3},{"uid":295623777,"face":"http://i0.hdslb.com/bfs/face/06d21e961074e23dfe0829b124e07850bd8f9458.jpg","score":"13","uname":"千兆端口","rank":2,"guard_level":0},{"uid":21103541,"face":"https://i2.hdslb.com/bfs/face/d7c2fe4aec87f36d145dfd80c405ac11a721311a.jpg","score":"12","uname":"slkrast","rank":3,"guard_level":0},{"uid":291399612,"face":"https://i0.hdslb.com/bfs/face/8aede0d719ef1e7a44e2e1a103a46cb569a81366.jpg","score":"10","uname":"不甜的冬瓜糖不甜","rank":4,"guard_level":0},{"uid":1359564720,"face":"https://i0.hdslb.com/bfs/face/9d71de2f3bc32ead729793044e215358da9f6248.jpg","score":"10","uname":"嘉然今天吃草莓捏_","rank":5,"guard_level":0},{"uid":479218569,"face":"https://i0.hdslb.com/bfs/face/13417d46c7750e5de78f34433560c9fa32b8efa9.jpg","score":"10","uname":"Uvall-","rank":6,"guard_level":0},{"uid":1381287077,"face":"https://i2.hdslb.com/bfs/face/21fbd836754c1788ad9e0dd683c72cfb9415ea05.jpg","score":"8","uname":"王牌泰菲","rank":7,"guard_level":3}],"rank_type":"gold-rank"}},{"cmd":"DANMU_MSG","info":[[0,1,25,5566168,1672488081712,-880507445,0,"f9c81faf",0,0,0,"",0,"{}","{}",{"mode":0,"show_player_type":0,"extra":"{\"send_from_me\":false,\"mode\":0,\"color\":5566168,\"dm_type\":0,\"font_size\":25,\"player_mode\":1,\"show_player_type\":0,\"content\":\"cfm你开门啊，我知道你在家\",\"user_hash\":\"4190642095\",\"emoticon_unique\":\"\",\"bulge_display\":0,\"recommend_score\":2,\"main_state_dm_color\":\"\",\"objective_state_dm_color\":\"\",\"direction\":0,\"pk_direction\":0,\"quartet_direction\":0,\"anniversary_crowd\":0,\"yeah_space_type\":\"\",\"yeah_space_url\":\"\",\"jump_to_url\":\"\",\"space_type\":\"\",\"space_url\":\"\",\"animation\":{},\"emots\":null}"},{"activity_identity":"","activity_source":0,"not_show":0}],"cfm你开门啊，我知道你在家",[295353299,"我说我是鹅你信不信",0,0,0,10000,1,""],[10,"雏草姬","永雏塔菲",22603245,9272486,"",0,9272486,9272486,9272486,0,1,1265680561],[1,0,9868950,">50000",0],["",""],0,0,null,{"ts":1672488081,"ct":"EBC8BF83"},0,0,null,null,0,49]},{"cmd":"SEND_GIFT","data":{"action":"投喂","batch_combo_id":"","batch_combo_send":null,"beatId":"","biz_source":"live","blind_gift":null,"broadcast_id":0,"coin_type":"silver","combo_resources_id":1,"combo_send":null,"combo_stay_time":3,"combo_total_coin":0,"crit_prob":0,"demarcation":1,"discount_price":0,"dmscore":20,"draw":0,"effect":0,"effect_block":1,"face":"https://i1.hdslb.com/bfs/baselabs/74238e16acf88aa810e2a2ef31416c8d34fbc13e.png","face_effect_id":0,"face_effect_type":0,"float_sc_resource_id":0,"giftId":1,"giftName":"辣条","giftType":5,"gold":0,"guard_level":0,"is_first":true,"is_join_receiver":false,"is_naming":false,"is_special_batch":0,"magnification":1,"medal_info":{"anchor_roomid":0,"anchor_uname":"","guard_level":0,"icon_id":0,"is_lighted":1,"medal_color":6126494,"medal_color_border":6126494,"medal_color_end":6126494,"medal_color_start":6126494,"medal_level":7,"medal_name":"雏草姬","special":"","target_id":1265680561},"name_color":"","num":1,"original_gift_name":"","price":100,"rcost":66758956,"receive_user_info":{"uid":1265680561,"uname":"永雏塔菲"},"remain":29,"rnd":"1672488081120600016","send_master":null,"silver":0,"super":0,"super_batch_gift_num":0,"super_gift_num":0,"svga_block":0,"switch":true,"tag_image":"","tid":"1672488081120600016","timestamp":1672488081,"top_list":null,"total_coin":100,"uid":670620736,"uname":"肖战粉丝梅麻"}},{"cmd":"DANMU_MSG","info":[[0,1,25,5816798,1672488081923,1672488028,0,"b6d719da",0,0,0,"",0,"{}","{}",{"mode":0,"show_player_type":0,"extra":"{\"send_from_me\":false,\"mode\":0,\"color\":5816798,\"dm_type\":0,\"font_size\":25,\"player_mode\":1,\"show_player_type\":0,\"content\":\"呃呃\",\"user_hash\":\"3067550170\",\"emoticon_unique\":\"\",\"bulge_display\":0,\"recommend_score\":0,\"main_state_dm_color\":\"\",\"objective_state_dm_color\":\"\",\"direction\":0,\"pk_direction\":0,\"quartet_direction\":0,\"anniversary_crowd\":0,\"yeah_space_type\":\"\",\"yeah_space_url\":\"\",\"jump_to_url\":\"\",\"space_type\":\"\",\"space_url\":\"\",\"animation\":{},\"emots\":null}"},{"activity_identity":"","activity_source":0,"not_show":0}],"呃呃",[630070452,"永雏糖菲",0,0,0,10000,1,""],[18,"雏草姬","永雏塔菲",22603245,13081892,"",0,13081892,13081892,13081892,0,1,1265680561],[10,0,9868950,">50000",0],["",""],0,0,null,{"ts":1672488081,"ct":"8C809BFD"},0,0,null,null,0,63]},{"cmd":"SEND_GIFT","data":{"action":"投喂","batch_combo_id":"","batch_combo_send":null,"beatId":"","biz_source":"live","blind_gift":null,"broadcast_id":0,"coin_type":"silver","combo_resources_id":1,"combo_send":null,"combo_stay_time":3,"combo_total_coin":0,"crit_prob":0,"demarcation":1,"discount_price":0,"dmscore":20,"draw":0,"effect":0,"effect_block":1,"face":"https://i1.hdslb.com/bfs/baselabs/74238e16acf88aa810e2a2ef31416c8d34fbc13e.png","face_effect_id":0,"face_effect_type":0,"float_sc_resource_id":0,"giftId":1,"giftName":"辣条","giftType":5,"gold":0,"guard_level":0,"is_first":true,"is_join_receiver":false,"is_naming":false,"is_special_batch":0,"magnification":1,"medal_info":{"anchor_roomid":0,"anchor_uname":"","guard_level":0,"icon_id":0,"is_lighted":1,"medal_color":6126494,"medal_color_border":6126494,"medal_color_end":6126494,"medal_color_start":6126494,"medal_level":7,"medal_name":"雏草姬","special":"","target_id":1265680561},"name_color":"","num":1,"original_gift_name":"","price":100,"rcost":66758956,"receive_user_info":{"uid":1265680561,"uname":"永雏塔菲"},"remain":28,"rnd":"1672488081120600019","send_master":null,"silver":0,"super":0,"super_batch_gift_num":0,"super_gift_num":0,"svga_block":0,"switch":true,"tag_image":"","tid":"1672488081120600019","timestamp":1672488081,"top_list":null,"total_coin":100,"uid":670620736,"uname":"肖战粉丝梅麻"}},{"cmd":"INTERACT_WORD","data":{"contribution":{"grade":0},"dmscore":20,"fans_medal":{"anchor_roomid":25836285,"guard_level":3,"icon_id":0,"is_lighted":1,"medal_color":1725515,"medal_color_border":6809855,"medal_color_end":5414290,"medal_color_start":1725515,"medal_level":21,"medal_name":"负分男","score":50001380,"special":"","target_id":2049801772},"identities":[3,1],"is_spread":0,"msg_type":1,"privilege_type":0,"roomid":22603245,"score":1722499461079,"spread_desc":"","spread_info":"","tail_icon":0,"timestamp":1672488081,"trigger_time":1672488079946078500,"uid":51410662,"uname":"离别好事_","uname_color":""}},{"cmd":"INTERACT_WORD","data":{"contribution":{"grade":0},"dmscore":16,"fans_medal":{"anchor_roomid":21013446,"guard_level":0,"icon_id":0,"is_lighted":0,"medal_color":1725515,"medal_color_border":12632256,"medal_color_end":12632256,"medal_color_start":12632256,"medal_level":21,"medal_name":"Luu民","score":50001481,"special":"","target_id":387636363},"identities":[1],"is_spread":0,"msg_type":1,"privilege_type":0,"roomid":22603245,"score":1672488081504,"spread_desc":"","spread_info":"","tail_icon":0,"timestamp":1672488081,"trigger_time":1672488080349721000,"uid":251443153,"uname":"FIENhg","uname_color":""}},{"cmd":"DANMU_MSG","info":[[0,1,25,16777215,1672488082099,218081491,0,"a90b8a02",0,0,0,"",0,"{}","{}",{"mode":0,"show_player_type":0,"extra":"{\"send_from_me\":false,\"mode\":0,\"color\":16777215,\"dm_type\":0,\"font_size\":25,\"player_mode\":1,\"show_player_type\":0,\"content\":\"开门喵\",\"user_hash\":\"2836105730\",\"emoticon_unique\":\"\",\"bulge_display\":0,\"recommend_score\":8,\"main_state_dm_color\":\"\",\"objective_state_dm_color\":\"\",\"direction\":0,\"pk_direction\":0,\"quartet_direction\":0,\"anniversary_crowd\":0,\"yeah_space_type\":\"\",\"yeah_space_url\":\"\",\"jump_to_url\":\"\",\"space_type\":\"\",\"space_url\":\"\",\"animation\":{},\"emots\":null}"},{"activity_identity":"","activity_source":0,"not_show":0}],"开门喵",[258086217,"イケベニン",0,0,0,10000,1,""],[5,"棺人痴","東雪蓮Official",22816111,6126494,"",0,6126494,6126494,6126494,0,1,1437582453],[4,0,9868950,">50000",0],["",""],0,0,null,{"ts":1672488082,"ct":"34C1DC45"},0,0,null,null,0,21]},{"cmd":"SEND_GIFT","data":{"action":"投喂","batch_combo_id":"","batch_combo_send":null,"beatId":"","biz_source":"live","blind_gift":null,"broadcast_id":0,"coin_type":"silver","combo_resources_id":1,"combo_send":null,"combo_stay_time":3,"combo_total_coin":0,"crit_prob":0,"demarcation":1,"discount_price":0,"dmscore":20,"draw":0,"effect":0,"effect_block":1,"face":"https://i1.hdslb.com/bfs/baselabs/74238e16acf88aa810e2a2ef31416c8d34fbc13e.png","face_effect_id":0,"face_effect_type":0,"float_sc_resource_id":0,"giftId":1,"giftName":"辣条","giftType":5,"gold":0,"guard_level":0,"is_first":true,"is_join_receiver":false,"is_naming":false,"is_special_batch":0,"magnification":1,"medal_info":{"anchor_roomid":0,"anchor_uname":"","guard_level":0,"icon_id":0,"is_lighted":1,"medal_color":6126494,"medal_color_border":6126494,"medal_color_end":6126494,"medal_color_start":6126494,"medal_level":7,"medal_name":"雏草姬","special":"","target_id":1265680561},"name_color":"","num":1,"original_gift_name":"","price":100,"rcost":66758957,"receive_user_info":{"uid":1265680561,"uname":"永雏塔菲"},"remain":27,"rnd":"1672488082120600002","send_master":null,"silver":0,"super":0,"super_batch_gift_num":0,"super_gift_num":0,"svga_block":0,"switch":true,"tag_image":"","tid":"1672488082120600002","timestamp":1672488082,"top_list":null,"total_coin":100,"uid":670620736,"uname":"肖战粉丝梅麻"}},{"cmd":"DANMU_MSG","info":[[0,1,25,16777215,1672488082174,1672480566,0,"be93fb0f",0,0,5,"#1453BAFF,#4C2263A2,#3353BAFF",0,"{}","{}",{"mode":0,"show_player_type":0,"extra":"{\"send_from_me\":false,\"mode\":0,\"color\":16777215,\"dm_type\":0,\"font_size\":25,\"player_mode\":1,\"show_player_type\":0,\"content\":\"喵喵喵\",\"user_hash\":\"3197369103\",\"emoticon_unique\":\"\",\"bulge_display\":0,\"recommend_score\":6,\"main_state_dm_color\":\"\",\"objective_state_dm_color\":\"\",\"direction\":0,\"pk_direction\":0,\"quartet_direction\":0,\"anniversary_crowd\":0,\"yeah_space_type\":\"\",\"yeah_space_url\":\"\",\"jump_to_url\":\"\",\"space_type\":\"\",\"space_url\":\"\",\"animation\":{},\"emots\":null}"},{"activity_identity":"","activity_source":0,"not_show":0}],"喵喵喵",[269757906,"永雏安啼",0,0,0,10000,1,"#00D1F1"],[27,"雏草姬","永雏塔菲",22603245,398668,"",0,6809855,398668,6850801,3,1,1265680561],[23,0,5805790,">50000",0],["",""],0,3,null,{"ts":1672488082,"ct":"2CE94368"},0,0,null,null,0,105]},{"cmd":"DANMU_MSG","info":[[0,1,25,5566168,1672488082199,950964864,0,"199bf7e7",0,0,0,"",0,"{}","{}",{"mode":0,"show_player_type":0,"extra":"{\"send_from_me\":false,\"mode\":0,\"color\":5566168,\"dm_type\":0,\"font_size\":25,\"player_mode\":1,\"show_player_type\":0,\"content\":\"爹\",\"user_hash\":\"429651943\",\"emoticon_unique\":\"\",\"bulge_display\":0,\"recommend_score\":6,\"main_state_dm_color\":\"\",\"objective_state_dm_color\":\"\",\"direction\":0,\"pk_direction\":0,\"quartet_direction\":0,\"anniversary_crowd\":0,\"yeah_space_type\":\"\",\"yeah_space_url\":\"\",\"jump_to_url\":\"\",\"space_type\":\"\",\"space_url\":\"\",\"animation\":{},\"emots\":null}"},{"activity_identity":"","activity_source":0,"not_show":0}],"爹",[58915742,"二师兄-猪",0,0,0,10000,1,""],[7,"雏草姬","永雏塔菲",22603245,6126494,"",0,6126494,6126494,6126494,0,1,1265680561],[21,0,5805790,">50000",0],["",""],0,0,null,{"ts":1672488082,"ct":"A79F5784"},0,0,null,null,0,70]}]],"packetLen":3173,"headerLen":16,"ver":3,"op":5,"seq":0}