{"body":[[{"cmd":"DANMU_MSG","info":[[0,1,25,5566168,1676380805855,1834431567,0,"a7be5094",0,0,0,"",0,"{}","{}",{"mode":0,"show_player_type":0,"extra":"{\"send_from_me\":false,\"mode\":0,\"color\":5566168,\"dm_type\":0,\"font_size\":25,\"player_mode\":1,\"show_player_type\":0,\"content\":\"好好好\",\"user_hash\":\"2814267540\",\"emoticon_unique\":\"\",\"bulge_display\":0,\"recommend_score\":1,\"main_state_dm_color\":\"\",\"objective_state_dm_color\":\"\",\"direction\":0,\"pk_direction\":0,\"quartet_direction\":0,\"anniversary_crowd\":0,\"yeah_space_type\":\"\",\"yeah_space_url\":\"\",\"jump_to_url\":\"\",\"space_type\":\"\",\"space_url\":\"\",\"animation\":{},\"emots\":null}"},{"activity_identity":"","activity_source":0,"not_show":0}],"好好好",[309428025,"Z芃瑶",0,0,0,10000,1,""],[11,"酷萨","阿萨Aza",21696950,9272486,"",0,9272486,9272486,9272486,0,1,480680646],[3,0,9868950,">50000",0],["",""],0,0,null,{"ts":1676380805,"ct":"F5D56D03"},0,0,null,null,0,70]},{"cmd":"DANMU_MSG","info":[[0,1,25,5816798,1676380805963,2032201047,0,"9c68c247",0,0,0,"",0,"{}","{}",{"mode":0,"show_player_type":0,"extra":"{\"send_from_me\":false,\"mode\":0,\"color\":5816798,\"dm_type\":0,\"font_size\":25,\"player_mode\":1,\"show_player_type\":0,\"content\":\"好好好\",\"user_hash\":\"2624111175\",\"emoticon_unique\":\"\",\"bulge_display\":0,\"recommend_score\":2,\"main_state_dm_color\":\"\",\"objective_state_dm_color\":\"\",\"direction\":0,\"pk_direction\":0,\"quartet_direction\":0,\"anniversary_crowd\":0,\"yeah_space_type\":\"\",\"yeah_space_url\":\"\",\"jump_to_url\":\"\",\"space_type\":\"\",\"space_url\":\"\",\"animation\":{},\"emots\":null}"},{"activity_identity":"","activity_source":0,"not_show":0}],"好好好",[255836670,"池末l",0,0,0,10000,1,""],[16,"酷萨","阿萨Aza",21696950,12478086,"",0,12478086,12478086,12478086,0,1,480680646],[12,0,6406234,">50000",0],["",""],0,0,null,{"ts":1676380805,"ct":"AFEFCEA"},0,0,null,null,0,63]},{"cmd":"DANMU_MSG","info":[[0,1,25,5566168,1676380805997,1259368446,0,"4d524f51",0,0,0,"",0,"{}","{}",{"mode":0,"show_player_type":0,"extra":"{\"send_from_me\":false,\"mode\":0,\"color\":5566168,\"dm_type\":0,\"font_size\":25,\"player_mode\":1,\"show_player_type\":0,\"content\":\"好好好\",\"user_hash\":\"1297239889\",\"emoticon_unique\":\"\",\"bulge_display\":0,\"recommend_score\":5,\"main_state_dm_color\":\"\",\"objective_state_dm_color\":\"\",\"direction\":0,\"pk_direction\":0,\"quartet_direction\":0,\"anniversary_crowd\":0,\"yeah_space_type\":\"\",\"yeah_space_url\":\"\",\"jump_to_url\":\"\",\"space_type\":\"\",\"space_url\":\"\",\"animation\":{},\"emots\":null}"},{"activity_identity":"","activity_source":0,"not_show":0}],"好好好",[381635367,"阿祇---",0,0,0,10000,1,""],[13,"酷萨","阿萨Aza",21696950,12478086,"",0,12478086,12478086,12478086,0,1,480680646],[0,0,9868950,">50000",0],["",""],0,0,null,{"ts":1676380805,"ct":"A0E21885"},0,0,null,null,0,49]},{"cmd":"DANMU_MSG","info":[[0,1,25,14893055,1676380805995,-1660687508,0,"7af5dc67",0,0,5,"#1453BAFF,#4C2263A2,#3353BAFF",0,"{}","{}",{"mode":0,"show_player_type":0,"extra":"{\"send_from_me\":false,\"mode\":0,\"color\":14893055,\"dm_type\":0,\"font_size\":25,\"player_mode\":1,\"show_player_type\":0,\"content\":\"好好好\",\"user_hash\":\"2062933095\",\"emoticon_unique\":\"\",\"bulge_display\":0,\"recommend_score\":0,\"main_state_dm_color\":\"\",\"objective_state_dm_color\":\"\",\"direction\":0,\"pk_direction\":0,\"quartet_direction\":0,\"anniversary_crowd\":0,\"yeah_space_type\":\"\",\"yeah_space_url\":\"\",\"jump_to_url\":\"\",\"space_type\":\"\",\"space_url\":\"\",\"animation\":{},\"emots\":null}"},{"activity_identity":"","activity_source":0,"not_show":0}],"好好好",[398855914,"许久_未见",0,0,0,10000,1,"#00D1F1"],[23,"酷萨","阿萨Aza",21696950,1725515,"",0,6809855,1725515,5414290,3,1,480680646],[10,0,9868950,">50000",0],["",""],0,3,null,{"ts":1676380805,"ct":"6EDA15F6"},0,0,null,null,0,105]},{"cmd":"DANMU_MSG","info":[[0,1,25,16777215,1676380806153,-1145467577,0,"fc189d13",0,0,0,"",0,"{}","{}",{"mode":0,"show_player_type":0,"extra":"{\"send_from_me\":false,\"mode\":0,\"color\":16777215,\"dm_type\":0,\"font_size\":25,\"player_mode\":1,\"show_player_type\":0,\"content\":\"好好好\",\"user_hash\":\"4229471507\",\"emoticon_unique\":\"\",\"bulge_display\":0,\"recommend_score\":2,\"main_state_dm_color\":\"\",\"objective_state_dm_color\":\"\",\"direction\":0,\"pk_direction\":0,\"quartet_direction\":0,\"anniversary_crowd\":0,\"yeah_space_type\":\"\",\"yeah_space_url\":\"\",\"jump_to_url\":\"\",\"space_type\":\"\",\"space_url\":\"\",\"animation\":{},\"emots\":null}"},{"activity_identity":"","activity_source":0,"not_show":0}],"好好好",[3493113968462481,"伦敦敦",0,0,0,10000,1,""],[],[0,0,9868950,">50000",0],["",""],0,0,null,{"ts":1676380806,"ct":"A5C1040E"},0,0,null,null,0,7]},{"cmd":"DANMU_MSG","info":[[0,1,25,5566168,1676380806170,-906926091,0,"4efa1cd4",0,0,0,"",0,"{}","{}",{"mode":0,"show_player_type":0,"extra":"{\"send_from_me\":false,\"mode\":0,\"color\":5566168,\"dm_type\":0,\"font_size\":25,\"player_mode\":1,\"show_player_type\":0,\"content\":\"好好好\",\"user_hash\":\"1325014228\",\"emoticon_unique\":\"\",\"bulge_display\":0,\"recommend_score\":9,\"main_state_dm_color\":\"\",\"objective_state_dm_color\":\"\",\"direction\":0,\"pk_direction\":0,\"quartet_direction\":0,\"anniversary_crowd\":0,\"yeah_space_type\":\"\",\"yeah_space_url\":\"\",\"jump_to_url\":\"\",\"space_type\":\"\",\"space_url\":\"\",\"animation\":{},\"emots\":null}"},{"activity_identity":"","activity_source":0,"not_show":0}],"好好好",[1587830639,"我是一个烂匣子",0,0,0,10000,1,""],[13,"酷萨","阿萨Aza",21696950,12478086,"",0,12478086,12478086,12478086,0,1,480680646],[0,0,9868950,">50000",0],["",""],0,0,null,{"ts":1676380806,"ct":"C5118CD4"},0,0,null,null,0,49]},{"cmd":"DANMU_MSG","info":[[0,4,25,14893055,1676380806198,-1623847306,0,"9e98f73a",0,0,5,"#1453BAFF,#4C2263A2,#3353BAFF",0,"{}","{}",{"mode":0,"show_player_type":0,"extra":"{\"send_from_me\":false,\"mode\":0,\"color\":14893055,\"dm_type\":0,\"font_size\":25,\"player_mode\":4,\"show_player_type\":0,\"content\":\"情人节快乐\",\"user_hash\":\"2660824890\",\"emoticon_unique\":\"\",\"bulge_display\":0,\"recommend_score\":6,\"main_state_dm_color\":\"\",\"objective_state_dm_color\":\"\",\"direction\":0,\"pk_direction\":0,\"quartet_direction\":0,\"anniversary_crowd\":0,\"yeah_space_type\":\"\",\"yeah_space_url\":\"\",\"jump_to_url\":\"\",\"space_type\":\"\",\"space_url\":\"\",\"animation\":{},\"emots\":null}"},{"activity_identity":"","activity_source":0,"not_show":0}],"情人节快乐",[1326124739,"顾柚柚柚柚柚柚柚柚",0,0,0,10000,1,"#00D1F1"],[22,"酷萨","阿萨Aza",21696950,1725515,"",0,6809855,1725515,5414290,3,1,480680646],[7,0,9868950,">50000",0],["",""],0,3,null,{"ts":1676380806,"ct":"87AE4EBE"},0,0,null,null,0,105]},{"cmd":"DANMU_MSG","info":[[0,1,25,5566168,1676380806248,-394395047,0,"cbb2ea54",0,0,0,"",0,"{}","{}",{"mode":0,"show_player_type":0,"extra":"{\"send_from_me\":false,\"mode\":0,\"color\":5566168,\"dm_type\":0,\"font_size\":25,\"player_mode\":1,\"show_player_type\":0,\"content\":\"好好好\",\"user_hash\":\"3417500244\",\"emoticon_unique\":\"\",\"bulge_display\":0,\"recommend_score\":6,\"main_state_dm_color\":\"\",\"objective_state_dm_color\":\"\",\"direction\":0,\"pk_direction\":0,\"quartet_direction\":0,\"anniversary_crowd\":0,\"yeah_space_type\":\"\",\"yeah_space_url\":\"\",\"jump_to_url\":\"\",\"space_type\":\"\",\"space_url\":\"\",\"animation\":{},\"emots\":null}"},{"activity_identity":"","activity_source":0,"not_show":0}],"好好好",[1804615985,"不纯洁的搓澡球",0,0,0,10000,1,""],[11,"酷萨","阿萨Aza",21696950,9272486,"",0,9272486,9272486,9272486,0,1,480680646],[0,0,9868950,">50000",0],["",""],0,0,null,{"ts":1676380806,"ct":"8EDFFEE0"},0,0,null,null,0,49]},{"cmd":"DANMU_MSG","info":[[0,1,25,5566168,1676380806250,-800370158,0,"c4da2ae7",0,0,0,"",0,"{}","{}",{"mode":0,"show_player_type":0,"extra":"{\"send_from_me\":false,\"mode\":0,\"color\":5566168,\"dm_type\":0,\"font_size\":25,\"player_mode\":1,\"show_player_type\":0,\"content\":\"好好好\",\"user_hash\":\"3302632167\",\"emoticon_unique\":\"\",\"bulge_display\":0,\"recommend_score\":9,\"main_state_dm_color\":\"\",\"objective_state_dm_color\":\"\",\"direction\":0,\"pk_direction\":0,\"quartet_direction\":0,\"anniversary_crowd\":0,\"yeah_space_type\":\"\",\"yeah_space_url\":\"\",\"jump_to_url\":\"\",\"space_type\":\"\",\"space_url\":\"\",\"animation\":{},\"emots\":null}"},{"activity_identity":"","activity_source":0,"not_show":0}],"好好好",[1797185335,"祝你周周开心",0,0,0,10000,1,""],[],[0,0,9868950,">50000",0],["",""],0,0,null,{"ts":1676380806,"ct":"3C098F5C"},0,0,null,null,0,7]},{"cmd":"DANMU_MSG","info":[[0,1,25,5566168,1676380806310,146986911,0,"7dd61444",0,0,0,"",1,{"bulge_display":1,"emoticon_unique":"room_21696950_1010","height":162,"in_player_area":1,"is_dynamic":1,"url":"http://i0.hdslb.com/bfs/garb/e2e2c5484a176cc8c583b83211decedf15b1fb66.png","width":162},"{}",{"mode":0,"show_player_type":0,"extra":"{\"send_from_me\":false,\"mode\":0,\"color\":5566168,\"dm_type\":1,\"font_size\":25,\"player_mode\":1,\"show_player_type\":0,\"content\":\"酷萨\",\"user_hash\":\"2111181892\",\"emoticon_unique\":\"room_21696950_1010\",\"bulge_display\":1,\"recommend_score\":9,\"main_state_dm_color\":\"\",\"objective_state_dm_color\":\"\",\"direction\":0,\"pk_direction\":0,\"quartet_direction\":0,\"anniversary_crowd\":0,\"yeah_space_type\":\"\",\"yeah_space_url\":\"\",\"jump_to_url\":\"\",\"space_type\":\"\",\"space_url\":\"\",\"animation\":{},\"emots\":null}"},{"activity_identity":"","activity_source":0,"not_show":0}],"酷萨",[1141392117,"捕捉小可爱233",0,0,0,10000,1,""],[12,"酷萨","阿萨Aza",21696950,9272486,"",0,9272486,9272486,9272486,0,1,480680646],[0,0,9868950,">50000",0],["",""],0,0,null,{"ts":1676380806,"ct":"A57F1952"},0,0,null,null,0,49]},{"cmd":"DANMU_MSG","info":[[0,1,25,14893055,1676380806318,-903293027,0,"0acf5e15",0,0,5,"#1453BAFF,#4C2263A2,#3353BAFF",0,"{}","{}",{"mode":0,"show_player_type":0,"extra":"{\"send_from_me\":false,\"mode\":0,\"color\":14893055,\"dm_type\":0,\"font_size\":25,\"player_mode\":1,\"show_player_type\":0,\"content\":\"好好好\",\"user_hash\":\"181362197\",\"emoticon_unique\":\"\",\"bulge_display\":0,\"recommend_score\":1,\"main_state_dm_color\":\"\",\"objective_state_dm_color\":\"\",\"direction\":0,\"pk_direction\":0,\"quartet_direction\":0,\"anniversary_crowd\":0,\"yeah_space_type\":\"\",\"yeah_space_url\":\"\",\"jump_to_url\":\"\",\"space_type\":\"\",\"space_url\":\"\",\"animation\":{},\"emots\":null}"},{"activity_identity":"","activity_source":0,"not_show":0}],"好好好",[381618700,"十七o_0",0,0,0,10000,1,"#00D1F1"],[],[8,0,9868950,">50000",0],["",""],0,3,null,{"ts":1676380806,"ct":"4CDC2216"},0,0,null,null,0,105]},{"cmd":"DANMU_MSG","info":[[0,1,25,5816798,1676380806347,602576555,0,"e8d0b5c5",0,0,0,"",0,"{}","{}",{"mode":0,"show_player_type":0,"extra":"{\"send_from_me\":false,\"mode\":0,\"color\":5816798,\"dm_type\":0,\"font_size\":25,\"player_mode\":1,\"show_player_type\":0,\"content\":\"可恶来晚了\",\"user_hash\":\"3905992133\",\"emoticon_unique\":\"\",\"bulge_display\":0,\"recommend_score\":0,\"main_state_dm_color\":\"\",\"objective_state_dm_color\":\"\",\"direction\":0,\"pk_direction\":0,\"quartet_direction\":0,\"anniversary_crowd\":0,\"yeah_space_type\":\"\",\"yeah_space_url\":\"\",\"jump_to_url\":\"\",\"space_type\":\"\",\"space_url\":\"\",\"animation\":{},\"emots\":null}"},{"activity_identity":"","activity_source":0,"not_show":0}],"可恶来晚了",[482321894,"温苒ink",0,0,0,10000,1,""],[15,"酷萨","阿萨Aza",21696950,12478086,"",0,12478086,12478086,12478086,0,1,480680646],[1,0,9868950,">50000",0],["",""],0,0,null,{"ts":1676380806,"ct":"F398EA73"},0,0,null,null,0,63]},{"cmd":"DANMU_MSG","info":[[0,4,25,14893055,1676380806394,791752498,0,"8998807e",0,0,5,"#1453BAFF,#4C2263A2,#3353BAFF",0,"{}","{}",{"mode":0,"show_player_type":0,"extra":"{\"send_from_me\":false,\"mode\":0,\"color\":14893055,\"dm_type\":0,\"font_size\":25,\"player_mode\":4,\"show_player_type\":0,\"content\":\"好\",\"user_hash\":\"2308472958\",\"emoticon_unique\":\"\",\"bulge_display\":0,\"recommend_score\":1,\"main_state_dm_color\":\"\",\"objective_state_dm_color\":\"\",\"direction\":0,\"pk_direction\":0,\"quartet_direction\":0,\"anniversary_crowd\":0,\"yeah_space_type\":\"\",\"yeah_space_url\":\"\",\"jump_to_url\":\"\",\"space_type\":\"\",\"space_url\":\"\",\"animation\":{},\"emots\":null}"},{"activity_identity":"","activity_source":0,"not_show":0}],"好",[15435028,"快对愿逸说愿意",0,0,0,10000,1,"#00D1F1"],[27,"酷萨","阿萨Aza",21696950,398668,"",0,6809855,398668,6850801,3,1,480680646],[20,0,6406234,">50000",0],["",""],0,3,null,{"ts":1676380806,"ct":"54AA70A3"},0,0,null,null,0,105]},{"cmd":"INTERACT_WORD","data":{"contribution":{"grade":0},"core_user_type":0,"dmscore":12,"fans_medal":{"anchor_roomid":21737386,"guard_level":0,"icon_id":0,"is_lighted":1,"medal_color":9272486,"medal_color_border":9272486,"medal_color_end":9272486,"medal_color_start":9272486,"medal_level":11,"medal_name":"嚣章","score":22532,"special":"","target_id":9066351},"identities":[3,1],"is_spread":0,"msg_type":1,"privilege_type":0,"roomid":21696950,"score":1676413337876,"spread_desc":"","spread_info":"","tail_icon":0,"timestamp":1676380805,"trigger_time":1676380804764114700,"uid":14945929,"uname":"璐璐゛","uname_color":""}},{"cmd":"INTERACT_WORD","data":{"contribution":{"grade":0},"core_user_type":0,"dmscore":2,"fans_medal":{"anchor_roomid":0,"guard_level":0,"icon_id":0,"is_lighted":0,"medal_color":0,"medal_color_border":0,"medal_color_end":0,"medal_color_start":0,"medal_level":0,"medal_name":"","score":0,"special":"","target_id":0},"identities":[1],"is_spread":0,"msg_type":1,"privilege_type":0,"roomid":21696950,"score":1676380805410,"spread_desc":"","spread_info":"","tail_icon":0,"timestamp":1676380805,"trigger_time":1676380804279617800,"uid":1219355346,"uname":"困几夜了","uname_color":""}},{"cmd":"DANMU_MSG","info":[[0,1,25,5816798,1676380806464,-669817993,0,"1c4816f9",0,0,0,"",0,"{}","{}",{"mode":0,"show_player_type":0,"extra":"{\"send_from_me\":false,\"mode\":0,\"color\":5816798,\"dm_type\":0,\"font_size\":25,\"player_mode\":1,\"show_player_type\":0,\"content\":\"好好好\",\"user_hash\":\"474486521\",\"emoticon_unique\":\"\",\"bulge_display\":0,\"recommend_score\":3,\"main_state_dm_color\":\"\",\"objective_state_dm_color\":\"\",\"direction\":0,\"pk_direction\":0,\"quartet_direction\":0,\"anniversary_crowd\":0,\"yeah_space_type\":\"\",\"yeah_space_url\":\"\",\"jump_to_url\":\"\",\"space_type\":\"\",\"space_url\":\"\",\"animation\":{},\"emots\":null}"},{"activity_identity":"","activity_source":0,"not_show":0}],"好好好",[1550702478,"一百个以内算单推",0,0,0,10000,1,""],[16,"酷萨","阿萨Aza",21696950,12478086,"",0,12478086,12478086,12478086,0,1,480680646],[2,0,9868950,">50000",0],["",""],0,0,null,{"ts":1676380806,"ct":"6EB593FE"},0,0,null,null,0,63]},{"cmd":"DANMU_MSG","info":[[0,1,25,5566168,1676380806554,738100573,0,"806bbe9d",0,0,0,"",0,"{}","{}",{"mode":0,"show_player_type":0,"extra":"{\"send_from_me\":false,\"mode\":0,\"color\":5566168,\"dm_type\":0,\"font_size\":25,\"player_mode\":1,\"show_player_type\":0,\"content\":\"好好好\",\"user_hash\":\"2154544797\",\"emoticon_unique\":\"\",\"bulge_display\":0,\"recommend_score\":4,\"main_state_dm_color\":\"\",\"objective_state_dm_color\":\"\",\"direction\":0,\"pk_direction\":0,\"quartet_direction\":0,\"anniversary_crowd\":0,\"yeah_space_type\":\"\",\"yeah_space_url\":\"\",\"jump_to_url\":\"\",\"space_type\":\"\",\"space_url\":\"\",\"animation\":{},\"emots\":null}"},{"activity_identity":"","activity_source":0,"not_show":0}],"好好好",[102589258,"黒のローブ",0,0,0,10000,1,""],[10,"酷萨","阿萨Aza",21696950,9272486,"",0,9272486,9272486,9272486,0,1,480680646],[0,0,9868950,">50000",0],["",""],0,0,null,{"ts":1676380806,"ct":"5AC5D5AE"},0,0,null,null,0,49]},{"cmd":"DANMU_MSG","info":[[0,1,25,14893055,1676380806589,83534482,0,"5b67bf55",0,0,5,"#1453BAFF,#4C2263A2,#3353BAFF",0,"{}","{}",{"mode":0,"show_player_type":0,"extra":"{\"send_from_me\":false,\"mode\":0,\"color\":14893055,\"dm_type\":0,\"font_size\":25,\"player_mode\":1,\"show_player_type\":0,\"content\":\"好好好\",\"user_hash\":\"1533525845\",\"emoticon_unique\":\"\",\"bulge_display\":0,\"recommend_score\":1,\"main_state_dm_color\":\"\",\"objective_state_dm_color\":\"\",\"direction\":0,\"pk_direction\":0,\"quartet_direction\":0,\"anniversary_crowd\":0,\"yeah_space_type\":\"\",\"yeah_space_url\":\"\",\"jump_to_url\":\"\",\"space_type\":\"\",\"space_url\":\"\",\"animation\":{},\"emots\":null}"},{"activity_identity":"","activity_source":0,"not_show":0}],"好好好",[1630774411,"-奧利-",0,0,0,10000,1,"#00D1F1"],[25,"酷萨","阿萨Aza",21696950,398668,"",0,6809855,398668,6850801,3,1,480680646],[11,0,6406234,">50000",0],["",""],0,3,null,{"ts":1676380806,"ct":"99BD1CA6"},0,0,null,null,0,105]},{"cmd":"DANMU_MSG","info":[[0,4,25,14893055,1676380806633,11984614,0,"ea254bac",0,0,5,"#1453BAFF,#4C2263A2,#3353BAFF",0,"{}","{}",{"mode":0,"show_player_type":0,"extra":"{\"send_from_me\":false,\"mode\":0,\"color\":14893055,\"dm_type\":0,\"font_size\":25,\"player_mode\":4,\"show_player_type\":0,\"content\":\"好好好好\",\"user_hash\":\"3928312748\",\"emoticon_unique\":\"\",\"bulge_display\":0,\"recommend_score\":9,\"main_state_dm_color\":\"\",\"objective_state_dm_color\":\"\",\"direction\":0,\"pk_direction\":0,\"quartet_direction\":0,\"anniversary_crowd\":0,\"yeah_space_type\":\"\",\"yeah_space_url\":\"\",\"jump_to_url\":\"\",\"space_type\":\"\",\"space_url\":\"\",\"animation\":{},\"emots\":null}"},{"activity_identity":"","activity_source":0,"not_show":0}],"好好好好",[97224497,"小桐是梧桐树的桐",0,0,0,10000,1,"#00D1F1"],[23,"酷萨","阿萨Aza",21696950,1725515,"",0,6809855,1725515,5414290,3,1,480680646],[5,0,9868950,">50000",0],["",""],0,3,null,{"ts":1676380806,"ct":"B2E33523"},0,0,null,null,0,105]},{"cmd":"DANMU_MSG","info":[[0,4,25,14893055,1676380806665,853037585,0,"790ca6a6",0,0,5,"#1453BAFF,#4C2263A2,#3353BAFF",0,"{}","{}",{"mode":0,"show_player_type":0,"extra":"{\"send_from_me\":false,\"mode\":0,\"color\":14893055,\"dm_type\":0,\"font_size\":25,\"player_mode\":4,\"show_player_type\":0,\"content\":\"好好好\",\"user_hash\":\"2030872230\",\"emoticon_unique\":\"\",\"bulge_display\":0,\"recommend_score\":1,\"main_state_dm_color\":\"\",\"objective_state_dm_color\":\"\",\"direction\":0,\"pk_direction\":0,\"quartet_direction\":0,\"anniversary_crowd\":0,\"yeah_space_type\":\"\",\"yeah_space_url\":\"\",\"jump_to_url\":\"\",\"space_type\":\"\",\"space_url\":\"\",\"animation\":{},\"emots\":null}"},{"activity_identity":"","activity_source":0,"not_show":0}],"好好好",[41647686,"是秋堇不是秋葵",0,0,0,10000,1,"#00D1F1"],[22,"酷萨","阿萨Aza",21696950,1725515,"",0,6809855,1725515,5414290,3,1,480680646],[4,0,9868950,">50000",0],["",""],0,3,null,{"ts":1676380806,"ct":"6B981591"},0,0,null,null,0,105]},{"cmd":"DANMU_MSG","info":[[0,4,25,14893055,1676380806712,388207993,0,"c9501acd",0,0,5,"#1453BAFF,#4C2263A2,#3353BAFF",0,"{}","{}",{"mode":0,"show_player_type":0,"extra":"{\"send_from_me\":false,\"mode\":0,\"color\":14893055,\"dm_type\":0,\"font_size\":25,\"player_mode\":4,\"show_player_type\":0,\"content\":\"好好好\",\"user_hash\":\"3377470157\",\"emoticon_unique\":\"\",\"bulge_display\":0,\"recommend_score\":8,\"main_state_dm_color\":\"\",\"objective_state_dm_color\":\"\",\"direction\":0,\"pk_direction\":0,\"quartet_direction\":0,\"anniversary_crowd\":0,\"yeah_space_type\":\"\",\"yeah_space_url\":\"\",\"jump_to_url\":\"\",\"space_type\":\"\",\"space_url\":\"\",\"animation\":{},\"emots\":null}"},{"activity_identity":"","activity_source":0,"not_show":0}],"好好好",[497952915,"这下我真成单推了",0,0,0,10000,1,"#00D1F1"],[23,"酷萨","阿萨Aza",21696950,1725515,"",0,6809855,1725515,5414290,3,1,480680646],[9,0,9868950,">50000",0],["",""],0,3,null,{"ts":1676380806,"ct":"4DA4DAA4"},0,0,null,null,0,105]},{"cmd":"DANMU_MSG","info":[[0,1,25,5566168,1676380806720,791876102,0,"e3bfa764",0,0,0,"",0,"{}","{}",{"mode":0,"show_player_type":0,"extra":"{\"send_from_me\":false,\"mode\":0,\"color\":5566168,\"dm_type\":0,\"font_size\":25,\"player_mode\":1,\"show_player_type\":0,\"content\":\"好好好\",\"user_hash\":\"3820988260\",\"emoticon_unique\":\"\",\"bulge_display\":0,\"recommend_score\":3,\"main_state_dm_color\":\"\",\"objective_state_dm_color\":\"\",\"direction\":0,\"pk_direction\":0,\"quartet_direction\":0,\"anniversary_crowd\":0,\"yeah_space_type\":\"\",\"yeah_space_url\":\"\",\"jump_to_url\":\"\",\"space_type\":\"\",\"space_url\":\"\",\"animation\":{},\"emots\":null}"},{"activity_identity":"","activity_source":0,"not_show":0}],"好好好",[103799032,"子小玉金金金",0,0,0,10000,1,""],[14,"酷萨","阿萨Aza",21696950,12478086,"",0,12478086,12478086,12478086,0,1,480680646],[18,0,6406234,">50000",0],["",""],0,0,null,{"ts":1676380806,"ct":"F3D2B2E4"},0,0,null,null,0,49]},{"cmd":"DANMU_MSG","info":[[0,1,25,16777215,1676380806731,863035712,0,"36f714de",0,0,0,"",0,"{}","{}",{"mode":0,"show_player_type":0,"extra":"{\"send_from_me\":false,\"mode\":0,\"color\":16777215,\"dm_type\":0,\"font_size\":25,\"player_mode\":1,\"show_player_type\":0,\"content\":\"好好好\",\"user_hash\":\"922162398\",\"emoticon_unique\":\"\",\"bulge_display\":0,\"recommend_score\":7,\"main_state_dm_color\":\"\",\"objective_state_dm_color\":\"\",\"direction\":0,\"pk_direction\":0,\"quartet_direction\":0,\"anniversary_crowd\":0,\"yeah_space_type\":\"\",\"yeah_space_url\":\"\",\"jump_to_url\":\"\",\"space_type\":\"\",\"space_url\":\"\",\"animation\":{},\"emots\":null}"},{"activity_identity":"","activity_source":0,"not_show":0}],"好好好",[3493122346584822,"I_Linlin_L",0,0,0,10000,1,""],[],[0,0,9868950,">50000",0],["",""],0,0,null,{"ts":1676380806,"ct":"E8D57C2C"},0,0,null,null,0,7]},{"cmd":"DANMU_MSG","info":[[0,1,25,14893055,1676380806741,2041926538,0,"a5754449",0,0,5,"#1453BAFF,#4C2263A2,#3353BAFF",0,"{}","{}",{"mode":0,"show_player_type":0,"extra":"{\"send_from_me\":false,\"mode\":0,\"color\":14893055,\"dm_type\":0,\"font_size\":25,\"player_mode\":1,\"show_player_type\":0,\"content\":\"好好好\",\"user_hash\":\"2775925833\",\"emoticon_unique\":\"\",\"bulge_display\":0,\"recommend_score\":1,\"main_state_dm_color\":\"\",\"objective_state_dm_color\":\"\",\"direction\":0,\"pk_direction\":0,\"quartet_direction\":0,\"anniversary_crowd\":0,\"yeah_space_type\":\"\",\"yeah_space_url\":\"\",\"jump_to_url\":\"\",\"space_type\":\"\",\"space_url\":\"\",\"animation\":{},\"emots\":null}"},{"activity_identity":"","activity_source":0,"not_show":0}],"好好好",[188814344,"9w9999999",0,0,0,10000,1,"#00D1F1"],[21,"酷萨","阿萨Aza",21696950,1725515,"",0,6809855,1725515,5414290,3,1,480680646],[3,0,9868950,">50000",0],["",""],0,3,null,{"ts":1676380806,"ct":"AC9B1DED"},0,0,null,null,0,105]}]],"packetLen":2430,"headerLen":16,"ver":3,"op":5,"seq":0}