{"body":[[{"cmd":"DANMU_MSG","info":[[0,1,25,5566168,1672505379367,2072520125,0,"756db603",0,0,0,"",0,"{}","{}",{"mode":0,"show_player_type":0,"extra":"{\"send_from_me\":false,\"mode\":0,\"color\":5566168,\"dm_type\":0,\"font_size\":25,\"player_mode\":1,\"show_player_type\":0,\"content\":\"晓音姐嘎人了\",\"user_hash\":\"1970124291\",\"emoticon_unique\":\"\",\"bulge_display\":0,\"recommend_score\":2,\"main_state_dm_color\":\"\",\"objective_state_dm_color\":\"\",\"direction\":0,\"pk_direction\":0,\"quartet_direction\":0,\"anniversary_crowd\":0,\"yeah_space_type\":\"\",\"yeah_space_url\":\"\",\"jump_to_url\":\"\",\"space_type\":\"\",\"space_url\":\"\",\"animation\":{},\"emots\":null}"},{"activity_identity":"","activity_source":0,"not_show":0}],"晓音姐嘎人了",[6982345,"超级下班王",0,0,0,10000,1,""],[11,"晓音组","红晓音Akane",411318,9272486,"",0,9272486,9272486,9272486,0,1,899804],[14,0,6406234,">50000",0],["",""],0,0,null,{"ts":1672505379,"ct":"FBE61D97"},0,0,null,null,0,49]},{"cmd":"DANMU_MSG","info":[[0,1,25,65532,1672505379574,1672504971,0,"5185bc30",0,0,0,"",0,"{}","{}",{"mode":0,"show_player_type":0,"extra":"{\"send_from_me\":false,\"mode\":0,\"color\":65532,\"dm_type\":0,\"font_size\":25,\"player_mode\":1,\"show_player_type\":0,\"content\":\"?\",\"user_hash\":\"1367718960\",\"emoticon_unique\":\"\",\"bulge_display\":0,\"recommend_score\":2,\"main_state_dm_color\":\"\",\"objective_state_dm_color\":\"\",\"direction\":0,\"pk_direction\":0,\"quartet_direction\":0,\"anniversary_crowd\":0,\"yeah_space_type\":\"\",\"yeah_space_url\":\"\",\"jump_to_url\":\"\",\"space_type\":\"\",\"space_url\":\"\",\"animation\":{},\"emots\":null}"},{"activity_identity":"","activity_source":0,"not_show":0}],"?",[34999281,"科学ACE",0,0,0,10000,1,""],[3,"晓音组","红晓音Akane",411318,6067854,"",0,6067854,6067854,6067854,0,1,899804],[39,0,10512625,36781,0],["",""],0,0,null,{"ts":1672505379,"ct":"C6AF2E77"},0,0,null,null,0,28]},{"cmd":"ONLINE_RANK_COUNT","data":{"count":566}},{"cmd":"DANMU_MSG","info":[[0,1,25,16777215,1672505379976,83151488,0,"2030cb4e",0,0,0,"",0,"{}","{}",{"mode":0,"show_player_type":0,"extra":"{\"send_from_me\":false,\"mode\":0,\"color\":16777215,\"dm_type\":0,\"font_size\":25,\"player_mode\":1,\"show_player_type\":0,\"content\":\"晓音姐唱得gn！\",\"user_hash\":\"540068686\",\"emoticon_unique\":\"\",\"bulge_display\":0,\"recommend_score\":5,\"main_state_dm_color\":\"\",\"objective_state_dm_color\":\"\",\"direction\":0,\"pk_direction\":0,\"quartet_direction\":0,\"anniversary_crowd\":0,\"yeah_space_type\":\"\",\"yeah_space_url\":\"\",\"jump_to_url\":\"\",\"space_type\":\"\",\"space_url\":\"\",\"animation\":{},\"emots\":null}"},{"activity_identity":"","activity_source":0,"not_show":0}],"晓音姐唱得gn！",[1407392,"底格六",0,0,0,10000,1,""],[],[12,0,6406234,">50000",0],["",""],0,0,null,{"ts":1672505379,"ct":"7283626B"},0,0,null,null,0,7]},{"cmd":"DANMU_MSG","info":[[0,1,25,5816798,1672505380035,-1327877781,0,"9f43db75",0,0,0,"",1,{"bulge_display":1,"emoticon_unique":"room_411318_2177","height":162,"in_player_area":1,"is_dynamic":1,"url":"http://i0.hdslb.com/bfs/garb/efbbe3bda9f57d7c6d86d1767957c7a943f35f9b.png","width":162},"{}",{"mode":0,"show_player_type":0,"extra":"{\"send_from_me\":false,\"mode\":0,\"color\":5816798,\"dm_type\":1,\"font_size\":25,\"player_mode\":1,\"show_player_type\":0,\"content\":\"问号\",\"user_hash\":\"2672024437\",\"emoticon_unique\":\"room_411318_2177\",\"bulge_display\":1,\"recommend_score\":5,\"main_state_dm_color\":\"\",\"objective_state_dm_color\":\"\",\"direction\":0,\"pk_direction\":0,\"quartet_direction\":0,\"anniversary_crowd\":0,\"yeah_space_type\":\"\",\"yeah_space_url\":\"\",\"jump_to_url\":\"\",\"space_type\":\"\",\"space_url\":\"\",\"animation\":{},\"emots\":null}"},{"activity_identity":"","activity_source":0,"not_show":0}],"问号",[123774885,"yui可可爱爱",0,0,0,10000,1,""],[19,"晓音组","红晓音Akane",411318,13081892,"",0,13081892,13081892,13081892,0,1,899804],[11,0,6406234,">50000",0],["",""],0,0,null,{"ts":1672505380,"ct":"591AB808"},0,0,null,null,0,63]},{"cmd":"DANMU_MSG","info":[[0,1,25,16777215,1672505380053,-1464689633,0,"b64abb7c",0,0,0,"",0,"{}","{}",{"mode":0,"show_player_type":0,"extra":"{\"send_from_me\":false,\"mode\":0,\"color\":16777215,\"dm_type\":0,\"font_size\":25,\"player_mode\":1,\"show_player_type\":0,\"content\":\"唱的次数越多，怪话就越多\",\"user_hash\":\"3058350972\",\"emoticon_unique\":\"\",\"bulge_display\":0,\"recommend_score\":0,\"main_state_dm_color\":\"\",\"objective_state_dm_color\":\"\",\"direction\":0,\"pk_direction\":0,\"quartet_direction\":0,\"anniversary_crowd\":0,\"yeah_space_type\":\"\",\"yeah_space_url\":\"\",\"jump_to_url\":\"\",\"space_type\":\"\",\"space_url\":\"\",\"animation\":{},\"emots\":null}"},{"activity_identity":"","activity_source":0,"not_show":0}],"唱的次数越多，怪话就越多",[104482171,"高晓宸",0,0,0,10000,1,""],[21,"抱豹豹","白神遥Haruka",21652717,1725515,"",0,6809855,1725515,5414290,3,1,477332594],[2,0,9868950,">50000",0],["",""],0,0,null,{"ts":1672505380,"ct":"4D6023BA"},0,0,null,null,0,70]},{"cmd":"DANMU_MSG","info":[[0,4,25,14893055,1672505380131,1672496289,0,"173518bd",0,0,5,"#1453BAFF,#4C2263A2,#3353BAFF",0,"{}","{}",{"mode":0,"show_player_type":0,"extra":"{\"send_from_me\":false,\"mode\":0,\"color\":14893055,\"dm_type\":0,\"font_size\":25,\"player_mode\":1,\"show_player_type\":0,\"content\":\"晓晓晓晓晓晓晓晓晓晓晓晓晓晓晓晓\",\"user_hash\":\"389355709\",\"emoticon_unique\":\"\",\"bulge_display\":0,\"recommend_score\":1,\"main_state_dm_color\":\"\",\"objective_state_dm_color\":\"\",\"direction\":0,\"pk_direction\":0,\"quartet_direction\":0,\"anniversary_crowd\":0,\"yeah_space_type\":\"\",\"yeah_space_url\":\"\",\"jump_to_url\":\"\",\"space_type\":\"\",\"space_url\":\"\",\"animation\":{},\"emots\":null}"},{"activity_identity":"","activity_source":0,"not_show":0}],"晓晓晓晓晓晓晓晓晓晓晓晓晓晓晓晓",[641038991,"红晓音Akane的铁单推",0,0,0,10000,1,"#00D1F1"],[23,"晓音组","红晓音Akane",411318,1725515,"",0,6809855,1725515,5414290,3,1,899804],[7,0,9868950,">50000",0],["",""],0,3,null,{"ts":1672505380,"ct":"C7A3D601"},0,0,null,null,0,105]}]],"packetLen":1243,"headerLen":16,"ver":3,"op":5,"seq":0}